[
  {
    "title": "空拍看台灣／從滿水位到幾乎見底 曾文水庫空拍全紀錄",
    "summary": "南台灣重要水源之一的曾文水庫，近期因降雨有限，加上持續供應民生與農業用水，蓄水情勢持續吃緊。雖然目前供水仍維持正常，但截至5月7日止，蓄水率已下滑至12％，逐漸逼近2021年百年大旱時的8.4％與2023年南部旱象時的7.3％，水情壓力再度浮現，再和去年一月初的畫面相比，當時滿水位時的曾文水庫湖面遼闊，碧綠水域幾乎延伸至山谷盡頭，如今僅過一年多卻出現巨大反差，隨著水位持續下探，大片乾裂裸露的庫底清晰可見，原本淹沒水中的地形、泥沙與枯木全都浮現，峽谷地貌與龜裂乾涸的庫底再度重現。 今年的梅雨鋒面雖替中北部帶來降雨，不過南部集水區受惠有限。水利署南區水資源分署統計，首波梅雨鋒面期間，曾文水庫上游累積雨量僅2.4毫米，對水庫進帳幫助相當有限。另一方面，水庫仍須持續供應民生用水，並支援農業灌溉，使得蓄水量持續下探。目前台南地區尚未亮起水情燈號，但隨著蓄水率逼近一成，外界也關注是否將重演過去旱災情況，形同進入「10％保衛戰」。 和去年相比，曾文水庫曾經連續半年維持滿水位，刷新營運52年來的紀錄，水位滿到上游的嘉義大埔情人公園及露營區通通泡在水中，罕見的狀況讓許多遊客都嘖嘖稱奇，好景不常今年開春後",
    "link": "https://udn.com/news/story/7326/9490252?from=udn-ch1_breaknews-1-0-news",
    "image": "https://pgw.udn.com.tw/gw/photo.php?u=https://uc.udn.com.tw/photo/t3/2026/05/08/34928831.jpg&M=1&s=Y&x=0&y=0&sw=1009&sh=672&exp=3600",
    "published_at": "2026-05-08 12:56"
  },
  {
    "title": "廚餘燒進焚化爐恐生戴奧辛 南投議員倡剩菜變豬飼料解垃圾危機",
    "summary": "南投縣每日產生大量廚餘，縣議員吳棋楠今天在議會質詢指出，若廚餘直接送入焚化爐燃燒，恐因含水量高導致爐內溫度驟降，增加戴奧辛生成風險，建議縣府評估設置公有廚餘處理廠，透過高溫高壓蒸煮、殺菌與脫水後，轉製為飼料，供養豬、養魚及家禽使用，從源頭解決廚餘過剩問題。",
    "link": "https://udn.com/news/story/7325/9490251?from=udn-ch1_breaknews-1-0-news",
    "image": "https://pgw.udn.com.tw/gw/photo.php?u=https://uc.udn.com.tw/photo/t3/2026/05/08/34928830.jpg&M=1&s=Y&x=0&y=0&sw=1280&sh=853&exp=3600",
    "published_at": "2026-05-08 12:56"
  },
  {
    "title": "桃園資收車司機昏厥釀1死6傷 市府開發低速防護系統6月上路實測",
    "summary": "桃園今年1月有資源回收車因司機突然昏厥暴衝，釀倒垃圾民眾1死6傷，民代要求檢討後，市府委託廠商開發防護裝置，預計5月底完成封測、6月上路實測。市長張善政表示，如果系統成熟，未來會想辦法推廣，考慮設獎勵機制，鼓勵公車業者也加裝。",
    "link": "https://udn.com/news/story/7324/9490250?from=udn-ch1_breaknews-1-0-news",
    "image": "https://pgw.udn.com.tw/gw/photo.php?u=https://uc.udn.com.tw/photo/t3/2026/05/08/34928829.jpg&M=1&s=Y&x=0&y=0&sw=1279&sh=853&exp=3600",
    "published_at": "2026-05-08 12:56"
  },
  {
    "title": "大陸48部門召開兩岸融合發展示範區會議 宋濤預告「更加有力的行動」",
    "summary": "大陸官方8日在北京召開了「建設兩岸融合發展示範區部省際工作會議」，研究下一步重點工作。中共中台辦主任宋濤強調，要以更加堅定的決心、更加務實的舉措、更加有力的行動，不斷開創兩岸融合發展示範區建設新局面。",
    "link": "https://udn.com/news/story/7331/9490247?from=udn-ch1_breaknews-1-0-news",
    "image": "https://pgw.udn.com.tw/gw/photo.php?u=https://uc.udn.com.tw/photo/t3/2026/05/08/34928828.jpg&M=1&s=Y&x=0&y=0&sw=1259&sh=839&exp=3600",
    "published_at": "2026-05-08 12:55"
  },
  {
    "title": "國王專機救援總統行程 馬文君轟：台灣外交淪落到臨時找出口",
    "summary": "賴清德總統日前結束訪問史瓦帝尼行程，完成任內首次非洲出訪。國民黨立委馬文君今天表示，總統出訪原已完成規畫與風險評估，卻在出發前夕突然取消原定安排，甚至改搭乘史國國王專機赴非，暴露出台灣國安與外交系統事前掌握能力出現問題。",
    "link": "https://udn.com/news/story/6656/9490246?from=udn-ch1_breaknews-1-0-news",
    "image": "https://pgw.udn.com.tw/gw/photo.php?u=https://uc.udn.com.tw/photo/t3/2026/05/08/34928827.jpg&M=1&s=Y&x=0&y=0&sw=1278&sh=852&exp=3600",
    "published_at": "2026-05-08 12:55"
  },
  {
    "title": "毒駕連環撞驚魂一瞬間 女乘客命危急轉院搶救",
    "summary": "嘉義市凌晨傳出嚴重交通事故，36歲吳姓男子涉嫌毒駕上路，行經新民路與徐州五街口時疑似未禮讓直行車，導致2車猛烈碰撞，釀成2人受傷、其中30歲蘇姓女乘客一度無呼吸心跳，經急救後恢復生命徵象，但傷勢嚴重，已轉送林口長庚醫院持續治療。",
    "link": "https://udn.com/news/story/7320/9490240?from=udn-ch1_breaknews-1-0-news",
    "image": "https://pgw.udn.com.tw/gw/photo.php?u=https://uc.udn.com.tw/photo/t3/2026/05/08/34928824.jpg&M=1&s=Y&x=0&y=0&sw=719&sh=479&exp=3600",
    "published_at": "2026-05-08 12:54"
  },
  {
    "title": "大雅第6公墓華麗轉身 親水綠地拚8月動工",
    "summary": "過去給人陰暗、雜亂印象的台中市大雅區第6公墓已完成遷葬，墓區即將迎來大變身。立委楊瓊瓔與台中市議員吳呈賢、吳建德今日邀集相關單位召開協調會，確認將結合農田水利署「三十五張分線」整體環境改善工程，預計投入約3千萬元經費，打造親水步道與綠地，最快於今年8月底動工。",
    "link": "https://udn.com/news/story/7325/9490239?from=udn-ch1_breaknews-1-0-news",
    "image": "https://pgw.udn.com.tw/gw/photo.php?u=https://uc.udn.com.tw/photo/t3/2026/05/08/34928821.jpg&M=1&s=Y&x=0&y=0&sw=1279&sh=853&exp=3600",
    "published_at": "2026-05-08 12:54"
  },
  {
    "title": "MLB／洋基19戰16勝與勇士並列第1 布恩談火星人傷退：是好孩子",
    "summary": "洋基隊今天啟用牛棚車輪戰，仍以9：2大勝遊騎兵隊，近19戰16勝。洋基目前26勝12敗與勇士隊並列全大聯盟第一，但光芒隊近14戰13勝，以0.5場勝差緊追在後。",
    "link": "https://udn.com/news/story/6999/9490122?from=udn-ch1_breaknews-1-0-news",
    "image": "https://pgw.udn.com.tw/gw/photo.php?u=https://uc.udn.com.tw/photo/t3/2026/05/08/34928654.jpg&M=1&s=Y&x=163&y=128&sw=958&sh=639&exp=3600",
    "published_at": "2026-05-08 12:54"
  },
  {
    "title": "台糖沙崙「循環宅」全台首例國際也關注 議員促台南社宅導入",
    "summary": "台糖打造的「沙崙智慧綠能循環住宅園區」236戶是全台首座循環住宅，除成為各縣市爭相取經的示範基地，更成為國際建築界關注焦點，台南市議員李宗霖今質詢都發局指出，未來興建社會住宅政策應導入「循環宅」概念，讓居住正義與淨零永續同步推進。都發局表示，沙崙循環宅是一個很好的案例，未來會努力研議將此概念運用於社宅會。",
    "link": "https://udn.com/news/story/7241/9490235?from=udn-ch1_breaknews-1-0-news",
    "image": "https://pgw.udn.com.tw/gw/photo.php?u=https://uc.udn.com.tw/photo/t3/2026/05/08/34928819.jpg&M=1&s=Y&x=0&y=0&sw=1098&sh=732&exp=3600",
    "published_at": "2026-05-08 12:54"
  },
  {
    "title": "中英關係升溫！英跨黨派議員本月中旬訪陸 2019年來首次",
    "summary": "路透8日報導，一個由英國跨黨派議員組成的代表團將於本月訪問中國大陸，這將是自2019年以來英國議員首次訪問中國，這也表明在英國首相施凱爾（Keir Starmer）今年1月訪陸以來，中英關係正在升溫。",
    "link": "https://udn.com/news/story/7331/9490234?from=udn-ch1_breaknews-1-0-news",
    "image": "https://pgw.udn.com.tw/gw/photo.php?u=https://uc.udn.com.tw/photo/t3/2026/05/08/34928818.jpg&M=1&s=Y&x=0&y=0&sw=1280&sh=853&exp=3600",
    "published_at": "2026-05-08 12:54"
  },
  {
    "title": "第一座三級汙水處理廠啟用 蔣萬安：汙水處理是看不見的良心工程",
    "summary": "台北市工務局衛生下水道工程增設水資源再生設施，其中民生水資源再生廠及環境教育館，今天啟用。目前是台北市首座三級汙水處理水資源再生廠，台北市長蔣萬安指出，汙水的處理是看不見的良心工程，透過技術，可以再生產1萬噸的再生水。",
    "link": "https://udn.com/news/story/7323/9490232?from=udn-ch1_breaknews-1-0-news",
    "image": "https://pgw.udn.com.tw/gw/photo.php?u=https://uc.udn.com.tw/photo/t3/2026/05/08/34928812.jpg&M=1&s=Y&x=0&y=0&sw=853&sh=569&exp=3600",
    "published_at": "2026-05-08 12:53"
  },
  {
    "title": "姊姊選縣長、弟弟選議員恐「雙殺」？謝衣鳯：國民黨團結有希望勝選",
    "summary": "國民黨下屆彰化縣長人選卡關，立法委員謝衣鳯強烈表達參選決心，她的弟弟謝典霖一改常態的勤快履行議長公務，地方傳出謝家姊弟一人選縣長、一人選縣議長恐「雙殺」都落選；謝衣鳯今表示，這是假設性推測，如果國民黨團結起來就能像去年大罷免大獲全勝。",
    "link": "https://udn.com/news/story/124652/9490231?from=udn-ch1_breaknews-1-0-news",
    "image": "https://pgw.udn.com.tw/gw/photo.php?u=https://uc.udn.com.tw/photo/t3/2026/05/08/34928811.jpg&M=1&s=Y&x=0&y=0&sw=1080&sh=720&exp=3600",
    "published_at": "2026-05-08 12:53"
  },
  {
    "title": "新竹地檢署召開打詐平台會議 高齡車手暴增成新警訊",
    "summary": "新竹地檢署今天召開「新竹地區詐欺預警中心暨地政機關預防不動產詐欺及逃逸外勞金融帳戶案件聯繫平台」會議，除盤點轄內詐欺犯罪趨勢、防制不動產詐欺及企業詐騙外，也特別點出「高齡車手」快速增加的新現象。統計顯示，65歲以上高齡車手案件從2024年僅2件，至去年暴增至22件，今年第一季已達13件，若趨勢不變，全年恐突破42人，顯示詐騙集團已不只鎖定高齡者當被害人，更進一步吸收成為犯罪工具。",
    "link": "https://udn.com/news/story/124490/9490230?from=udn-ch1_breaknews-1-0-news",
    "image": "https://pgw.udn.com.tw/gw/photo.php?u=https://uc.udn.com.tw/photo/t3/2026/05/08/34928808.png&M=1&s=Y&x=0&y=0&sw=1067&sh=711&exp=3600",
    "published_at": "2026-05-08 12:53"
  },
  {
    "title": "雲林某高職足球教練涉猥褻女學生 強吻、強抱長達5年",
    "summary": "雲林縣某高職傳出有足球教練涉嫌猥褻女學生，有女學生指控，教練從國中開始多次對她做出擁抱、親吻等肢體動作，時間長達5年，她因害怕不敢說，甚至為此做惡夢，直到日前其他教練在集訓前性平教育，她才意識到這是不對的行為，且有另名國中同學也曾有相似遭遇，憂心有更多人受害，決定勇敢舉報，該名教練目前仍在校任職，校方表示，接獲舉報後，已立案調查。",
    "link": "https://udn.com/news/story/7317/9490229?from=udn-ch1_breaknews-1-0-news",
    "image": "https://pgw.udn.com.tw/gw/photo.php?u=https://uc.udn.com.tw/photo/t3/2026/05/08/34928807.jpg&M=1&s=Y&x=0&y=0&sw=1143&sh=762&exp=3600",
    "published_at": "2026-05-08 12:52"
  },
  {
    "title": "台鐵屏東線潮州至南州電力故障不通 啟動公路接駁",
    "summary": "台鐵屏東線潮州至南州路段，上午因為電力設備故障路線暫時不通，影響旅客通行，台鐵啟動潮州至枋寮間公路接駁，並全力搶修。建議南下旅客出發前，先透過台鐵官網查詢最新列車延誤動態。",
    "link": "https://udn.com/news/story/7266/9490226?from=udn-ch1_breaknews-1-0-news",
    "image": "https://pgw.udn.com.tw/gw/photo.php?u=https://uc.udn.com.tw/photo/t3/2026/05/08/34928799.jpg&M=1&s=Y&x=0&y=0&sw=1080&sh=720&exp=3600",
    "published_at": "2026-05-08 12:51"
  },
  {
    "title": "影／基隆捷運2階麥金路路線出爐 市府：年底向交通提報為最佳方案",
    "summary": "基隆捷運第二階段兩路線沿舊台鐵路廊或安樂區麥金路如何走？藍綠兩位市長參選人市長謝國樑及議長童子瑋主張不同，近日引發基隆人熱議。基隆市政府今開記者會說明，指麥金路方案為最佳決策，路線規畫也出爐，可行性評估年底會出來，將向交通部建議為最優方案，工程開挖隧道技術沒有問題。",
    "link": "https://udn.com/news/story/7328/9490225?from=udn-ch1_breaknews-1-0-news",
    "image": "https://pgw.udn.com.tw/gw/photo.php?u=https://uc.udn.com.tw/photo/t3/2026/05/08/34928796.jpg&M=1&s=Y&x=0&y=0&sw=1279&sh=853&exp=3600",
    "published_at": "2026-05-08 12:50"
  },
  {
    "title": "MLB／大都會老將金布洛爾挨逆轉滿貫砲：我認為先三振了",
    "summary": "大都會今日作客洛磯主場，原在前段比賽取得2：0領先，後援投手金布洛爾（Craig Kimbrel）卻在第8局慘遭麥卡錫（Jake McCarthy）滿貫砲重擊，最終以2：6慘遭逆轉，無緣完成系列賽橫掃。",
    "link": "https://udn.com/news/story/6999/9490171?from=udn-ch1_breaknews-1-0-news",
    "image": "https://pgw.udn.com.tw/gw/photo.php?u=https://uc.udn.com.tw/photo/t3/2026/05/08/34928707.jpg&M=1&s=Y&x=0&y=0&sw=1280&sh=853&exp=3600",
    "published_at": "2026-05-08 12:44"
  },
  {
    "title": "我國8船舶滯留荷姆茲海峽 航港局：擬參考台塑君善輪模式",
    "summary": "針對近期中東局勢升溫、荷姆茲海峽航運安全受到關注，交通部航港局長葉協隆8日表示，交通部與外交部已於5月7日召開跨部會會議，研商我國船舶受困波灣海域的可能因應作法，目前外交部已透過相關管道與伊朗方面進行初步接觸，並同步洽詢理念相近國家的處理方式，作為我方後續參考。另外，台塑君善輪的做法也具備參考價值，後續也有望透過相同作法與伊朗接洽。",
    "link": "https://udn.com/news/story/7238/9490219?from=udn-ch1_breaknews-1-0-news",
    "image": "https://pgw.udn.com.tw/gw/photo.php?u=https://uc.udn.com.tw/photo/t3/2026/05/08/34928826.jpg&M=1&s=Y&x=0&y=0&sw=1280&sh=853&exp=3600",
    "published_at": "2026-05-08 12:43"
  },
  {
    "title": "繳稅最高10%回饋！台新 Richart 推一站式理財方案",
    "summary": "每逢五月報稅季，民眾資金壓力升溫，若善用數位金融工具，不僅能減輕負擔，更有機會將支出轉化為實質回饋。台新Richart今年繳稅季重磅推出一站式方案，整合信用卡與數位帳戶優勢，包含刷台新Richart卡最優分12期0利率、新戶最高10%回饋，以及開戶完成任務享LINE POINTS 300點與最高3.5%優利活儲。",
    "link": "https://udn.com/news/story/7243/9490218?from=udn-ch1_breaknews-1-0-news",
    "image": "https://pgw.udn.com.tw/gw/photo.php?u=https://p.udn.com.tw/upf/2017_news/noimg_cid6644_8.jpg",
    "published_at": "2026-05-08 12:43"
  },
  {
    "title": "澳洲新制留兩成 LNG 不出口 經部：我方既有合約無虞",
    "summary": "澳洲政府宣布重大能源改革，將自2027年7月1日起實施「國內天然氣儲備計畫」，要求出口商保留20%產量供應其國內市場。對此，經濟部表示，已於第一時間掌握澳洲相關政策發展，中油公司與澳洲供應商簽訂的中長期液化天然氣（LNG）採購合約不受影響。",
    "link": "https://udn.com/news/story/7238/9490216?from=udn-ch1_breaknews-1-0-news",
    "image": "https://pgw.udn.com.tw/gw/photo.php?u=https://p.udn.com.tw/upf/2017_news/noimg_cid6644_3.jpg",
    "published_at": "2026-05-08 12:41"
  },
  {
    "title": "影／愛爾麗針孔申訴破290件 盧秀燕：今要求業者刪「免責霸王條款」",
    "summary": "知名連鎖醫美集團「免責權」爆煙霧偵測器微型針孔監視器涉及偷拍事件，台中市長盧秀燕今天受訪時說，到今早八時，全國已有逾290件消費申訴，其中台中已有37件，台中市政府今派法制局和衛生局赴台中二分店，要求業者必須理賠，且不能要求免責權，保障消費者權益。",
    "link": "https://udn.com/news/story/124864/9490215?from=udn-ch1_breaknews-1-0-news",
    "image": "https://pgw.udn.com.tw/gw/photo.php?u=https://uc.udn.com.tw/photo/t3/2026/05/08/34928775.jpg&M=1&s=Y&x=0&y=0&sw=1280&sh=853&exp=3600",
    "published_at": "2026-05-08 12:41"
  },
  {
    "title": "又一全國連鎖醫美爆裝針孔偷拍 新北檢：視情況發動搜索",
    "summary": "愛爾麗針孔偷拍風暴方興未艾，又傳出另一連鎖醫美業者位於新北市板橋區的分店，也疑似安裝針孔偷拍病患，目前已由衛生單位及警方前往旗下分店稽查中。對此，新北地檢署證實，警方已就該案報請檢方指揮偵辦，目前仍屬行政稽查，未來檢方將視情況發動搜索。",
    "link": "https://udn.com/news/story/124864/9490213?from=udn-ch1_breaknews-1-0-news",
    "image": "https://pgw.udn.com.tw/gw/photo.php?u=https://uc.udn.com.tw/photo/t3/2026/05/08/34928771.jpg&M=1&s=Y&x=0&y=0&sw=1279&sh=853&exp=3600",
    "published_at": "2026-05-08 12:39"
  },
  {
    "title": "高雄銀改選 蘇建榮、李慶華、李怡慧皆當選獨董",
    "summary": "高雄銀行8日上午舉行股東常會並全面改選董事，共選出8名董事及5名獨立董事，根據當選名單顯示，在一般董事方面，高雄市政府取得三席，民股第一大股東晉禾也同樣取得三席、高雄陳家取得一席，另一席則是自然人董事。獨立董事方面，除了現任獨立董事汪渡村、蘇建榮續任外，前財政部政務次長李慶華、前財政部北區國稅局局長李怡慧也同樣當選。",
    "link": "https://udn.com/news/story/7239/9490203?from=udn-ch1_breaknews-1-0-news",
    "image": "https://pgw.udn.com.tw/gw/photo.php?u=https://uc.udn.com.tw/photo/t3/2026/05/08/34928863.jpg&M=1&s=Y&x=0&y=0&sw=1280&sh=853&exp=3600",
    "published_at": "2026-05-08 12:37"
  },
  {
    "title": "北投幼兒園爆班導施暴！拖把打幼童、不睡覺就打",
    "summary": "台北市北投一間幼兒園傳出班導涉及虐待幼童，包含拖把打幼童、彈小孩耳朵到瘀青、小朋友不睡覺就要跪地施暴。教育局今年2月起接獲通報即刻調查，涉案人員已於案發後次日離職，最高可裁罰60萬元。",
    "link": "https://udn.com/news/story/6885/9490200?from=udn-ch1_breaknews-1-0-news",
    "image": "https://pgw.udn.com.tw/gw/photo.php?u=https://p.udn.com.tw/upf/2017_news/noimg_cid11195_2.jpg",
    "published_at": "2026-05-08 12:36"
  },
  {
    "title": "新北捷運三鶯線擴大招募127名新血 最高起薪62K",
    "summary": "捷運三鶯線即將通車，新北捷運公司啟動「三鶯線暨既有路線」公開招募甄試，本次招募鎖定畢業季職場新鮮人及在地青年，共計釋出127個名額，其中「系統控制專員」於通過試用期考核後，薪資最高可達約6萬2000元。",
    "link": "https://udn.com/news/story/7323/9490196?from=udn-ch1_breaknews-1-0-news",
    "image": "https://pgw.udn.com.tw/gw/photo.php?u=https://uc.udn.com.tw/photo/t3/2026/05/08/34928751.jpg&M=1&s=Y&x=0&y=0&sw=1280&sh=853&exp=3600",
    "published_at": "2026-05-08 12:35"
  },
  {
    "title": "毒窟藏改造衝鋒槍 竹縣依托咪酯分裝場、市值破百萬",
    "summary": "桃園警察局中壢分局日前接獲情資，發現林姓嫌犯於新竹縣湖口鄉長嶺路一處民宅擁槍自重，並涉嫌販賣毒品維生，經專案小組長期蒐證發現，林嫌等人更涉嫌設置依托咪酯毒品分裝場所，被警方持搜索票破門查獲。",
    "link": "https://udn.com/news/story/7315/9490195?from=udn-ch1_breaknews-1-0-news",
    "image": "https://pgw.udn.com.tw/gw/photo.php?u=https://uc.udn.com.tw/photo/t3/2026/05/08/34928748.jpg&M=1&s=Y&x=0&y=0&sw=1079&sh=719&exp=3600",
    "published_at": "2026-05-08 12:35"
  },
  {
    "title": "不只愛爾麗偷拍！又傳板橋2醫美診所被搜 侯友宜：全面普查",
    "summary": "愛爾麗醫美集團陷入偷拍事件延燒，集團總裁常如山等3人遭收押，新北市板橋區又傳出2家醫美診所疑似裝有微型針孔監視器，也涉偷拍風波，新北市衛生局及警方今天上午聯手前往調查。",
    "link": "https://udn.com/news/story/124864/9490193?from=udn-ch1_breaknews-1-0-news",
    "image": "https://pgw.udn.com.tw/gw/photo.php?u=https://uc.udn.com.tw/photo/t3/2026/05/08/34928746.jpg&M=1&s=Y&x=0&y=0&sw=1244&sh=829&exp=3600",
    "published_at": "2026-05-08 12:32"
  },
  {
    "title": "影／藍委批檢察總長代理案違法 質疑「假代理、真獨裁」",
    "summary": "國民黨立法院黨團書記長林沛祥與立委羅智強、翁曉玲今天舉行記者會，質疑總統賴清德在最高檢察署檢察總長人事案遭立法院封殺後，仍指派徐錫祥代理檢察總長，批評相關做法涉及違法與濫權疑慮。",
    "link": "https://udn.com/news/story/6656/9490187?from=udn-ch1_breaknews-1-0-news",
    "image": "https://pgw.udn.com.tw/gw/photo.php?u=https://uc.udn.com.tw/photo/t3/2026/05/08/34928744.jpg&M=1&s=Y&x=0&y=0&sw=1234&sh=823&exp=3600",
    "published_at": "2026-05-08 12:31"
  },
  {
    "title": "699元起燒肉＋自助吧吃到飽！台中烤狀猿新店開幕 打卡加碼送生蠔",
    "summary": "台中燒肉控開吃！老井餐飲集團旗下人氣燒肉品牌「烤狀猿」，正式回歸台中南屯區，「新文心店」即日起正式進入試營運，除提供經典699元、超值799元、豪華海陸饗宴1,199元共3種吃到飽方案，更為慶祝開幕推出限時優惠，即日起至5月14日止，只要追蹤官方Threads帳號，並現場出示地標打卡畫面，每個帳號即可免費兌換生蠔1顆，每日限量100顆。",
    "link": "https://udn.com/news/story/7270/9490180?from=udn-ch1_breaknews-1-0-news",
    "image": "https://pgw.udn.com.tw/gw/photo.php?u=https://uc.udn.com.tw/photo/t3/2026/05/08/34928734.jpg&M=1&s=Y&x=0&y=0&sw=1280&sh=853&exp=3600",
    "published_at": "2026-05-08 12:28"
  },
  {
    "title": "批台電哭窮花百萬改標誌 王鴻薇指聶永真連拿交通部、中油、台電標案",
    "summary": "近期台電改變標誌，國民黨立委王鴻薇批台電「喊窮虧損」，卻花百萬標案改標誌。她更指設計師聶永真連拿台電、中油、交通部的標案。",
    "link": "https://udn.com/news/story/6656/9490179?from=udn-ch1_breaknews-1-0-news",
    "image": "https://pgw.udn.com.tw/gw/photo.php?u=https://uc.udn.com.tw/photo/t3/2026/05/08/34928733.jpg&M=1&s=Y&x=0&y=0&sw=1279&sh=852&exp=3600",
    "published_at": "2026-05-08 12:28"
  },
  {
    "title": "115國中會考要帶圓規嗎？前輩給建議 直尺、三角板需留意規定",
    "summary": "115年度國中教育會考將於母親節後舉行，5月16日（六）、17日（日）可說是全台國三生最重要的兩天。",
    "link": "https://udn.com/news/story/124826/9490117?from=udn-ch1_breaknews-1-0-news",
    "image": "https://pgw.udn.com.tw/gw/photo.php?u=https://uc.udn.com.tw/photo/t3/2026/05/08/34928645.jpg&M=1&s=Y&x=0&y=107&sw=1280&sh=853&exp=3600",
    "published_at": "2026-05-08 12:27"
  },
  {
    "title": "NBA／里夫斯復活飆31分無用 湖人下半場被雷霆打爆吞2連敗",
    "summary": "西區季後賽第二輪雷霆隊與湖人隊今天進行第二戰，儘管上半場雙方一路拉鋸，但雷霆在第三節靠著多點開花的攻勢單節灌進36分，將領先差距擴大到雙位數，加上末節外線手感甦醒，最終雷霆就以125：107擊敗湖人，將帶著2：0優勢前往洛杉磯作客。",
    "link": "https://udn.com/news/story/7002/9490178?from=udn-ch1_breaknews-1-0-news",
    "image": "https://pgw.udn.com.tw/gw/photo.php?u=https://uc.udn.com.tw/photo/t3/2026/05/08/34928743.jpg&M=1&s=Y&x=0&y=0&sw=1280&sh=853&exp=3600",
    "published_at": "2026-05-08 12:27"
  },
  {
    "title": "超瞎飛機餐！打開牛肉漢堡見「牛牛貼紙」配紙片火腿 乘客傻眼：懷疑人生",
    "summary": "飛機餐也會出現名不符實情況？有香港民眾日前搭乘大陸航空公司，空服員送飛機餐稱是「牛肉漢堡」，但當她打開包裝，發現裏頭沒有牛肉，反而是1張「牛牛圖案貼紙」配以薄火腿，亦傳來「一陣酸臭小黃瓜味」，因此傻眼表示「嚴重懷疑人生」。有網友笑稱漢堡賣相不佳，「看了就沒食慾」、「如果沒講，我會以為你搭北韓航空..……」，並質疑航空公司的餐食名不符實，「騙子」。",
    "link": "https://udn.com/news/story/7335/9490157?from=udn-ch1_breaknews-1-0-news",
    "image": "https://pgw.udn.com.tw/gw/photo.php?u=https://uc.udn.com.tw/photo/t3/2026/05/08/34928710.jpg&M=1&s=Y&x=0&y=119&sw=1280&sh=854&exp=3600",
    "published_at": "2026-05-08 12:27"
  },
  {
    "title": "鋒面通過中 專家：春雨延伸 偏像秋冬季鋒面型態",
    "summary": "鋒面逐漸通過，天氣風險公司資深顧問吳聖宇今天在臉書粉專「天氣職人-吳聖宇」表示，鋒面靠近後就分成兩部分，較明顯的在台灣東方海面，伴隨旺盛對流系統發展，對台灣陸地上沒有太大影響，台灣海峽這一側沒有看到明顯的對流系統，大多是中低層狀雲系，北部、東北部陸地上則是開始有東北季風南下遇到地形產生的降雨回波出現。這波整體看起來仍是春雨的延伸，甚至比較偏像是秋冬季鋒面的型態。",
    "link": "https://udn.com/news/story/7266/9490172?from=udn-ch1_breaknews-1-0-news",
    "image": "https://pgw.udn.com.tw/gw/photo.php?u=https://uc.udn.com.tw/photo/t3/2026/05/08/34928708.jpg&M=1&s=Y&x=0&y=0&sw=1078&sh=718&exp=3600",
    "published_at": "2026-05-08 12:24"
  },
  {
    "title": "影／北市首座三級再生水廠啟用 蔣萬安談鼠患同步清消",
    "summary": "台北市近期鼠患問題，甚至有老鼠出現在婚宴會館室內空間，引發外界關注。台北市長蔣萬安今天表示，台北市已正式啟動12個行政區全面大清消作業，並從中正區率先展開，要求相關局處與業者全面加強環境衛生管理。",
    "link": "https://udn.com/news/story/7323/9490170?from=udn-ch1_breaknews-1-0-news",
    "image": "https://pgw.udn.com.tw/gw/photo.php?u=https://uc.udn.com.tw/photo/t3/2026/05/08/34928705.jpg&M=1&s=Y&x=0&y=0&sw=1279&sh=853&exp=3600",
    "published_at": "2026-05-08 12:22"
  },
  {
    "title": "新台幣午盤升2.6分　暫收31.383元",
    "summary": "台北外匯市場新台幣兌美元今天中午暫收31.383元，升2.6分，成交金額9.45億美元",
    "link": "https://udn.com/news/story/7239/9490147?from=udn-ch1_breaknews-1-0-news",
    "image": "https://pgw.udn.com.tw/gw/photo.php?u=https://p.udn.com.tw/upf/2017_news/noimg_cid6644_7.jpg",
    "published_at": "2026-05-08 12:22"
  },
  {
    "title": "擴充算力太燒錢！「輝達親兒子」CoreWeave財測差 盤後股價重摔逾9%",
    "summary": "被稱為「輝達（NVIDIA）親兒子」的人工智慧（AI）基礎設施供應商CoreWeave上季營收雖高於預期，但淨損擴大，本季營收預測令市場失望，且上修全年資本支出區間的下緣，拖累股價盤後重挫逾9%。",
    "link": "https://udn.com/news/story/6811/9490168?from=udn-ch1_breaknews-1-0-news",
    "image": "https://pgw.udn.com.tw/gw/photo.php?u=https://uc.udn.com.tw/photo/t3/2026/05/08/34928702.jpg&M=1&s=Y&x=0&y=0&sw=1280&sh=853&exp=3600",
    "published_at": "2026-05-08 12:22"
  },
  {
    "title": "創泓科技發現新商機 搶攻無人載具安全領域",
    "summary": "創泓科技（7714）近日展示新平台，主要針對無人載具監控進行開發，保證其安全性，同時搭載多國語音系統，讓無人載具能夠被應用在更多領域。創泓科技董事長黃健寧表示，未來隨著無人載具滲透率進一步提升，其安全性需要更加被重視。",
    "link": "https://udn.com/news/story/7240/9490169?from=udn-ch1_breaknews-1-0-news",
    "image": "https://pgw.udn.com.tw/gw/photo.php?u=https://p.udn.com.tw/upf/2017_news/noimg_cid6644_1.jpg",
    "published_at": "2026-05-08 12:22"
  },
  {
    "title": "有單接不了！AI熱潮下缺料擴散 科技股營收獲利卡關",
    "summary": "隨著財報陸續揭露，一個明確趨勢浮現：AI需求暴增導致零組件供應短缺，供應鏈瓶頸正從記憶體擴散至晶圓、CPU、矽晶片與光學元件，衝擊科技業接單能力、獲利率與營收成長。",
    "link": "https://udn.com/news/story/6811/9490156?from=udn-ch1_breaknews-1-0-news",
    "image": "https://pgw.udn.com.tw/gw/photo.php?u=https://uc.udn.com.tw/photo/t3/2026/05/08/34928686.jpg&M=1&s=Y&x=0&y=0&sw=1279&sh=853&exp=3600",
    "published_at": "2026-05-08 12:17"
  },
  {
    "title": "歐義銳榮：發掘歐洲「隱形冠軍」 捕捉歐陸新成長引擎",
    "summary": "2026年以來，台灣股市與美股科技及AI巨頭屢創新高，台股漲幅更超過三成，令許多投資人開始擔憂市場過熱，積極尋求估值更具吸引力且能有效分散風險的標的。歐義銳榮資產管理指出，另一股強大的結構性成長力量正悄然在歐洲中小型企業中醞釀，2026年將成為布局歐陸「隱形冠軍」的關鍵契機。",
    "link": "https://udn.com/news/story/7238/9490155?from=udn-ch1_breaknews-1-0-news",
    "image": "https://pgw.udn.com.tw/gw/photo.php?u=https://p.udn.com.tw/upf/2017_news/noimg_cid6644_5.jpg",
    "published_at": "2026-05-08 12:16"
  },
  {
    "title": "美伊戰事影響鈍化 海外 ETF 熱度攀升",
    "summary": "美伊戰事影響鈍化，美股頻創新高，吸引投資人對海外股票型ETF的參與度升溫，買氣加上股價上升，海外股票型ETF總規模已達6,347億元，今年以來成長860億元。今年規模成長前五大海外ETF中，有兩檔主動式，主動統一全球創新（00988A）憑藉最強績效，成為規模成長第二大的海外ETF。",
    "link": "https://udn.com/news/story/123006/9490152?from=udn-ch1_breaknews-1-0-news",
    "image": "https://pgw.udn.com.tw/gw/photo.php?u=https://uc.udn.com.tw/photo/t3/2026/05/08/34928681.png&M=1&s=Y&x=0&y=0&sw=790&sh=527&exp=3600",
    "published_at": "2026-05-08 12:15"
  },
  {
    "title": "關鍵資源大戰 野村 ETF 率先卡位稀土三大戰略資產",
    "summary": "國際資本市場資金輪動加速，在科技創新浪潮推進的同時，稀缺關鍵資源正逐步躍升為驅動下一階段成長的核心主軸。野村投信正式推出全台首檔─野村稀土關鍵資源ETF（009821），一檔瞄準稀土、鈾礦與黃金三大稀缺戰略資產，協助投資人一次掌握產業升級、能源轉型與避險需求三大趨勢，切入未來十年全球最關鍵的資本機會。",
    "link": "https://udn.com/news/story/123006/9490150?from=udn-ch1_breaknews-1-0-news",
    "image": "https://pgw.udn.com.tw/gw/photo.php?u=https://uc.udn.com.tw/photo/t3/2026/05/08/34928679.jpg&M=1&s=Y&x=0&y=0&sw=1278&sh=852&exp=3600",
    "published_at": "2026-05-08 12:13"
  },
  {
    "title": "藥華藥4月營收創高、首次衝破20億元 股價大漲一舉站上季線",
    "summary": "台股8日震盪劇烈，盤中一度急殺800點，隨後在下跌300點附近震盪，生技股逆勢走高，股王藥華藥（6446）4月合併營收20.6億元，首次衝破20億元大關，年增68.35%，今日股價跳空上漲，盤中大漲逾9%，站上季線大關。",
    "link": "https://udn.com/news/story/7252/9490148?from=udn-ch1_breaknews-1-0-news",
    "image": "https://pgw.udn.com.tw/gw/photo.php?u=https://uc.udn.com.tw/photo/t3/2026/05/08/34928682.jpg&M=1&s=Y&x=0&y=237&sw=951&sh=634&exp=3600",
    "published_at": "2026-05-08 12:12"
  },
  {
    "title": "宏都拉斯有望與台復交？ 外交部：不設前提下推動雙邊關係發展",
    "summary": "宏都拉斯總統阿斯夫拉（Nasry Asfura）稱正在審查宏國前任總統與中國達成的協議，並可能促使宏國重新承認台灣。對此，外交部發言人蕭光偉表示，台灣作為全球可信賴的合作夥伴，外交部將秉持一貫不預設前提的態度，持續推動雙方關係的發展。",
    "link": "https://udn.com/news/story/6656/9490145?from=udn-ch1_breaknews-1-0-news",
    "image": "https://pgw.udn.com.tw/gw/photo.php?u=https://uc.udn.com.tw/photo/t3/2026/05/08/34928664.jpg&M=1&s=Y&x=0&y=0&sw=1279&sh=852&exp=3600",
    "published_at": "2026-05-08 12:11"
  },
  {
    "title": "耀穎上櫃首日開盤就飆漲269% 抽中1張大賺14.3萬元",
    "summary": "耀穎（7772）8日以每股53元掛牌上櫃，一開盤就跳空以196元開出，上漲143元，漲幅269.81%，股價一度衝高至196.5元，上漲143.5元，漲幅270.75%；中籤的投資人若開盤就賣，可獲利14.3萬元，抽中1張賺超過2.6張。",
    "link": "https://udn.com/news/story/7254/9490144?from=udn-ch1_breaknews-1-0-news",
    "image": "https://pgw.udn.com.tw/gw/photo.php?u=https://uc.udn.com.tw/photo/t3/2026/05/08/34928680.jpg&M=1&s=Y&x=0&y=0&sw=1280&sh=854&exp=3600",
    "published_at": "2026-05-08 12:11"
  },
  {
    "title": "華郵：CIA估伊朗在美封鎖下還能撐3個月以上",
    "summary": "美國中央情報局（CIA）本週提交政府決策官員的一份機密分析指出，伊朗於美國海上封鎖下至少還能再撐3到4個月，經濟才會出現...",
    "link": "https://udn.com/news/story/124061/9490109?from=udn-ch1_breaknews-1-0-news",
    "image": "https://pgw.udn.com.tw/gw/photo.php?u=https://p.udn.com.tw/upf/2017_news/noimg_cid7225_9.jpg",
    "published_at": "2026-05-08 12:10"
  },
  {
    "title": "中東戰爭第69天》美伊再交火川普淡化衝突 最新發展一次看",
    "summary": "美國與以色列聯手攻打伊朗進入第69天，儘管美伊在荷莫茲海峽（Straitof Hormuz）再度交火，美國總統川普試圖淡...",
    "link": "https://udn.com/news/story/124061/9490111?from=udn-ch1_breaknews-1-0-news",
    "image": "https://pgw.udn.com.tw/gw/photo.php?u=https://p.udn.com.tw/upf/2017_news/noimg_cid7225_2.jpg",
    "published_at": "2026-05-08 12:10"
  },
  {
    "title": "巴拉圭總統率團來訪 賴總統軍禮儀式歡迎",
    "summary": "巴拉圭共和國總統貝尼亞率團訪問台灣，賴清德總統今天率各部會首長以軍禮儀式歡迎來訪，賴總統感謝巴拉圭長期在國際場域為台灣發聲，期待兩國繼續深化合作，更深入推動雙方夥伴關係，使邦誼更佳深厚。",
    "link": "https://udn.com/news/story/6656/9490142?from=udn-ch1_breaknews-1-0-news",
    "image": "https://pgw.udn.com.tw/gw/photo.php?u=https://uc.udn.com.tw/photo/t3/2026/05/08/34928660.jpg&M=1&s=Y&x=0&y=0&sw=1279&sh=853&exp=3600",
    "published_at": "2026-05-08 12:10"
  },
  {
    "title": "聯發科被列處置股掀怒火！網狂轟制度落後：交易限制不合時宜",
    "summary": "IC設計大廠聯發科近日因股價短線漲幅過大，被列入分盤交易處置股，引發市場與PTT股板熱烈討論。有網友分享新聞指出，聯發科成為台股史上市值最大的處置股，連立委都在立法院質疑制度是否過時，金管會也承諾1個月內提出檢討報告。貼文曝光後，大量網友將矛頭對準「處置制度」，認為台股許多交易限制早已不合時宜，甚至嘲諷「亞洲納斯達克根本變笑話」。",
    "link": "https://udn.com/news/story/7251/9488305?from=udn-ch1_breaknews-1-0-news",
    "image": "https://pgw.udn.com.tw/gw/photo.php?u=https://uc.udn.com.tw/photo/t3/2026/05/07/34925878.jpg&M=1&x=&y=&sw=&sh=&exp=3600",
    "published_at": "2026-05-08 12:06"
  },
  {
    "title": "電影「航站情緣」翻版 海地夫妻滯台45天移民署協助返鄉",
    "summary": "一對海地籍夫妻今年1月5日自菲律賓馬尼拉搭機來台轉機，原欲前往帛琉，未料因無回程機票，遭帛琉移民單位拒絕入境並遣返回台，後續又陸續遭菲律賓及馬來西亞拒絕入境，受困桃園國際機場過境區長達45天。移民署國境事務大隊獲報後，積極協調航空公司、海地大使館及外交部等單位，最終於3月18日協助夫妻離境前往越南河內，並於3月24日再轉往柬埔寨金邊，展開返鄉行程。",
    "link": "https://udn.com/news/story/7320/9490127?from=udn-ch1_breaknews-1-0-news",
    "image": "https://pgw.udn.com.tw/gw/photo.php?u=https://uc.udn.com.tw/photo/t3/2026/05/08/34928647.jpg&M=1&s=Y&x=0&y=0&sw=1280&sh=853&exp=3600",
    "published_at": "2026-05-08 12:05"
  },
  {
    "title": "NBA／哈登季後賽又「軟手」 米契爾：一點都不擔心",
    "summary": "騎士隊「大鬍子」哈登（James Harden）今年季後賽第二輪狀態低迷，在與活塞隊系列賽的前兩場比賽都未能打出水準，包括今天的第二戰單場只有10分進帳，其中下半場僅有2次出手機會，昔日聯盟頭號得分手的風采盡失，不過搭檔米契爾（Donovan Mitchell）也強調一點都不擔心他的狀況。",
    "link": "https://udn.com/news/story/7002/9490121?from=udn-ch1_breaknews-1-0-news",
    "image": "https://pgw.udn.com.tw/gw/photo.php?u=https://uc.udn.com.tw/photo/t3/2026/05/08/34928656.jpg&M=1&s=Y&x=0&y=0&sw=1280&sh=854&exp=3600",
    "published_at": "2026-05-08 12:04"
  },
  {
    "title": "聯發科遭關禁閉卻成台股救星！IC 設計持續噴出 誰加入漲停行列？",
    "summary": "台股8日盤中劇烈震盪，加權指數一度急殺801點、失守41,200點，ABF載板、PCB、記憶體與部分AI高價股全面承壓。不過，才剛遭列入處置股的IC設計龍頭聯發科（2454），卻在股價回測3,500元關卡後強勢穩住，盤中漲幅仍逾5%，帶動IC設計族群逆勢走強，成為大盤跌勢收斂的關鍵救援主角。",
    "link": "https://udn.com/news/story/7253/9490104?from=udn-ch1_breaknews-1-0-news",
    "image": "https://pgw.udn.com.tw/gw/photo.php?u=https://uc.udn.com.tw/photo/t3/2026/05/08/34928637.jpg&M=1&s=Y&x=0&y=0&sw=1280&sh=853&exp=3600",
    "published_at": "2026-05-08 12:00"
  },
  {
    "title": "全國模範警察公布名單 高雄市刑大包辦3人",
    "summary": "警政署公布全國模範警察名單，高雄市警察局共有3名員警獲選，全數由刑事警察大隊包辦，分別為偵二隊偵查佐陳子鈞、偵八隊偵查佐盧玉鏵及科技犯罪偵查隊偵查佐連盈智。",
    "link": "https://udn.com/news/story/7320/9490101?from=udn-ch1_breaknews-1-0-news",
    "image": "https://pgw.udn.com.tw/gw/photo.php?u=https://uc.udn.com.tw/photo/t3/2026/05/08/34928586.jpg&M=1&s=Y&x=0&y=0&sw=1080&sh=720&exp=3600",
    "published_at": "2026-05-08 11:59"
  },
  {
    "title": "鐵飯碗不香了？女公務員想退休 夫見年薪喊少又不准她辭",
    "summary": "近日一名女性公務員在網路上發文抱怨，自己只是向丈夫透露「好想退休」的念頭，沒想到不僅遭到反對，還因真實薪資曝光後被嫌「賺太少」，讓她相當無奈。貼文曝光後，也引發大批網友討論公務員工作的優缺點，甚至掀起兩派論戰。",
    "link": "https://udn.com/news/story/7269/9489901?from=udn-ch1_breaknews-1-0-news",
    "image": "https://pgw.udn.com.tw/gw/photo.php?u=https://uc.udn.com.tw/photo/t3/2026/05/08/34928455.jpg&M=1&s=Y&x=0&y=0&sw=1280&sh=853&exp=3600",
    "published_at": "2026-05-08 11:58"
  },
  {
    "title": "換logo評價兩極 台電回應了：年輕同仁居多 期待公司發展新意象",
    "summary": "脆友發現台電默默更換掉由書法家于右任題字的logo，改用的新版logo出自設計師聶永真「永真急制設計工作室」，在網路上引發正反評價。台電表示，感謝各界關注提供寶貴意見，此次調整設計以「延續」為核心，保留「台電」字樣、三環與四道閃電等核心元素，重新整理字體比例與整體視覺設計，除延續台電熟悉印象，也期望展現與時俱進的企業形象。",
    "link": "https://udn.com/news/story/7269/9490098?from=udn-ch1_breaknews-1-0-news",
    "image": "https://pgw.udn.com.tw/gw/photo.php?u=https://uc.udn.com.tw/photo/t3/2026/05/08/34928583.jpg&M=1&s=Y&x=0&y=0&sw=1278&sh=853&exp=3600",
    "published_at": "2026-05-08 11:57"
  },
  {
    "title": "南亞 SAYA 機能環保賽衣連四年助攻 力挺2026台北101公益垂直馬拉松",
    "summary": "2026台北101公益垂直馬拉松將於5月9日盛大開跑。南亞（1303）連續第四年贊助賽事機能賽衣，透過旗下永續品牌SAYA提供約5,600件回收再製的高機能環保賽衣，將減碳行動與極限運動結合，藉由賽事凝聚社會正向力量，提升大眾對環境議題的關注與認同。",
    "link": "https://udn.com/news/story/7241/9490097?from=udn-ch1_breaknews-1-0-news",
    "image": "https://pgw.udn.com.tw/gw/photo.php?u=https://uc.udn.com.tw/photo/t3/2026/05/08/34928582.jpg&M=1&s=Y&x=0&y=0&sw=1279&sh=853&exp=3600",
    "published_at": "2026-05-08 11:57"
  },
  {
    "title": "7-ELEVEN「有肌商機」衝50億元！黃金滷蛋、水煮蛋擴大1,500店販售",
    "summary": "隨著健康意識年輕化，日常健身與體態維護帶動蛋白質補充剛需成長，統一超（2912）7-ELEVEN為滿足消費者需求提供多樣化「蛋白友好」飲食選擇，包括即食雞胸肉、即食蛋品、減醣蔬食等，其中更進一步擴大免剝殼風味蛋品「黃金滷蛋」與「黃金水煮蛋」販售，估計今年優質蛋白補充相關餐飲業績上看50億元，創造全新「有肌商機」帶動鮮食相關業績樂觀成長。",
    "link": "https://udn.com/news/story/7241/9490096?from=udn-ch1_breaknews-1-0-news",
    "image": "https://pgw.udn.com.tw/gw/photo.php?u=https://uc.udn.com.tw/photo/t3/2026/05/08/34928581.jpg&M=1&s=Y&x=0&y=0&sw=1280&sh=854&exp=3600",
    "published_at": "2026-05-08 11:57"
  },
  {
    "title": "NBA／「一同退休」藍圖恐破局？名記透露格林續約意願剩5成",
    "summary": "勇士老將格林（Draymond Green）今夏動向持續受到關注。根據《ClutchPoints》記者席格爾（Brett Siegel）透露，雖然勇士總教練柯爾（Steve Kerr）仍希望格林留隊，但目前雙方續約前景僅有「50／50」。",
    "link": "https://udn.com/news/story/7002/9490050?from=udn-ch1_breaknews-1-0-news",
    "image": "https://pgw.udn.com.tw/gw/photo.php?u=https://uc.udn.com.tw/photo/t3/2026/05/08/34928500.jpg&M=1&s=Y&x=0&y=0&sw=1280&sh=853&exp=3600",
    "published_at": "2026-05-08 11:57"
  },
  {
    "title": "反針孔啟動稽查兩周！北市警出動「鏡頭搜索器」 不肖業者慘了",
    "summary": "愛爾麗醫美診所針孔事件延燒，北市府今日啟動為期2周擴大反針孔稽查專案。衛生局開記者會強調，會以容易暴露、私密場所處無預警稽查，至少調查20家業者，同時若有不合格就會公布名單。",
    "link": "https://udn.com/news/story/7323/9490093?from=udn-ch1_breaknews-1-0-news",
    "image": "https://pgw.udn.com.tw/gw/photo.php?u=https://uc.udn.com.tw/photo/t3/2026/05/08/34928573.jpg&M=1&s=Y&x=0&y=0&sw=1280&sh=853&exp=3600",
    "published_at": "2026-05-08 11:57"
  },
  {
    "title": "國人手機贈股票金近億元女性成主力 偏愛三大 ETF",
    "summary": "永豐金（2890）證券領航數位投資生活圈，以股票禮品卡率先開啟「手機轉贈股票金」場域，主打「投資台股啟動金」全程不需實體現鈔，手機一鍵即可贈送/兌換投資台積電（2330）、元大台灣50（0050）等約近300檔熱門股，國人可在台股大AI時代趨勢下，輕鬆邀請親友一同參與經濟成長的豐厚果實。",
    "link": "https://udn.com/news/story/123006/9490090?from=udn-ch1_breaknews-1-0-news",
    "image": "https://pgw.udn.com.tw/gw/photo.php?u=https://p.udn.com.tw/upf/2017_news/noimg_cid6645_9.jpg",
    "published_at": "2026-05-08 11:56"
  }
]