[
  {
    "title": "遭川普嗆「打回石器時代」！伊朗軍方火大回應了",
    "summary": "法新社報導，美國總統川普於美東時間4月1日晚間就伊朗戰爭發表演說後，伊朗軍方發言人2日回應，接下來將升級攻勢「輾壓」以色列和美國，預告在敵人投降之前戰爭不會結束。",
    "link": "https://udn.com/news/story/124061/9419006?from=udn-ch1_breaknews-1-0-news",
    "image": "https://pgw.udn.com.tw/gw/photo.php?u=https://uc.udn.com.tw/photo/t3/2026/04/02/34821992.jpg&M=1&s=Y&x=0&y=0&sw=1280&sh=854&exp=3600",
    "published_at": "2026-04-02 14:20"
  },
  {
    "title": "過時10年逆襲！有線耳機銷量漲20% 明星紛紛佩戴出鏡",
    "summary": "近日，被淘汰了快10年的有線耳機意外走紅，多位時尚圈明星頻頻佩戴出鏡，成為耳機圈最受關注的現象級產品；調研機構Circana報告顯示，有線耳機在經歷長達五年銷售下滑後強勢反彈，2026年前三個月銷售額暴漲20%。",
    "link": "https://udn.com/news/story/7333/9418779?from=udn-ch1_breaknews-1-0-news",
    "image": "https://pgw.udn.com.tw/gw/photo.php?u=https://uc.udn.com.tw/photo/t3/2026/04/02/34821676.jpg&M=1&s=Y&x=0&y=0&sw=1277&sh=852&exp=3600",
    "published_at": "2026-04-02 14:19"
  },
  {
    "title": "午餐免費成嘉市長選戰焦點 張啓楷翁壽良接力喊延續免費加碼食安把關",
    "summary": "嘉義市長黃敏惠上午宣布，115學年度起國中小學營養午餐全面免費，成為教育政策重要里程碑，適逢市長選戰藍白民調登場，引爆藍白營市長參選人張啓楷、翁壽良競相表態，要在延續免費午餐既有政策基礎上，再加碼強化營養與食安把關。",
    "link": "https://udn.com/news/story/7326/9419004?from=udn-ch1_breaknews-1-0-news",
    "image": "https://pgw.udn.com.tw/gw/photo.php?u=https://uc.udn.com.tw/photo/t3/2026/04/02/34821987.jpg&M=1&s=Y&x=0&y=0&sw=1279&sh=853&exp=3600",
    "published_at": "2026-04-02 14:18"
  },
  {
    "title": "卡達LNG設施重損恐推升價格50% 台灣中油部分成本轉嫁給台電",
    "summary": "彭博分析師估計，由於卡達液化天然氣（LNG）設備遭到伊朗飛彈攻擊，設施受損嚴重，亞洲LNG價格可能大漲 50%，甚至可能觸及高峰每百萬英熱單位 30 美元，將嚴重侵蝕台灣中油在內亞洲LNG天然氣進口商的利潤。",
    "link": "https://udn.com/news/story/7238/9419003?from=udn-ch1_breaknews-1-0-news",
    "image": "https://pgw.udn.com.tw/gw/photo.php?u=https://uc.udn.com.tw/photo/t3/2026/04/02/34821986.jpg&M=1&s=Y&x=0&y=0&sw=1280&sh=853&exp=3600",
    "published_at": "2026-04-02 14:18"
  },
  {
    "title": "影／因應中東戰爭局勢 政院要求三鐵、客運、國內航線票價凍漲",
    "summary": "行政院副院長鄭麗君、行政院政務委員林明昕、陳時中、葉俊顯、經濟部次長何晉滄、衛福部次長莊人祥、農業部次長黃昭欽、法務部次長馮成中午一起出席行政院會後記者會，說明美伊戰爭爆發後因應措施。",
    "link": "https://udn.com/news/story/6656/9419002?from=udn-ch1_breaknews-1-0-news",
    "image": "https://pgw.udn.com.tw/gw/photo.php?u=https://uc.udn.com.tw/photo/t3/2026/04/02/34821982.jpg&M=1&s=Y&x=0&y=0&sw=1279&sh=853&exp=3600",
    "published_at": "2026-04-02 14:18"
  },
  {
    "title": "朱政騏捲共諜案民進黨火速開鍘！ 遭開除黨籍第一反應曝",
    "summary": "檢調再查獲綠營涉共諜案，被捲入的是通過初選的民進黨台北市中山大同議員參選人朱政騏，今遭民進黨火速開除黨籍，北市議員張茂楠今表示朱當下反應平靜，並表示尊重決定，至於後續中山大同提名是否補人，則由中央黨部決定。",
    "link": "https://udn.com/news/story/120838/9419001?from=udn-ch1_breaknews-1-0-news",
    "image": "https://pgw.udn.com.tw/gw/photo.php?u=https://uc.udn.com.tw/photo/t3/2026/04/02/34821975.jpg&M=1&s=Y&x=0&y=0&sw=1280&sh=853&exp=3600",
    "published_at": "2026-04-02 14:17"
  },
  {
    "title": "蛋糕是8吋還是6吋？實品不符硬拗「有加高」 店家慘被砲轟到關帳",
    "summary": "遇到婚禮壽宴、節日慶祝時，許多人還是會很有儀式感的訂個蛋糕享用。不過，有民眾疑惑「蛋糕尺寸」到底怎麼算，表示曾訂購一款8吋蛋糕，實際拿到卻是6吋大小，店家解釋是用「6吋加高模」，重量和八吋一樣，最後她因不懂行不再追問，但疑問至今未解。對此，眾人皆認為她被唬了，6吋做高還是6吋，不會變8吋。 原PO近日在Threads上問出一直壓在心底的疑惑「6吋加高的蛋糕會變成8吋嗎」？她表示，去年向某家蛋糕業者訂了8吋蛋糕，實際拿到的蛋糕卻比認知小上許多，拿尺一量也發現蛋糕直徑只有6吋，而非她要求的8吋。 詢問後，店家表示「統一使用六吋加高模，但內容物都和八吋一樣」，強調「可以自行上秤，絕對是八吋」，但原PO認為蛋糕本身不高，每家店也沒有固定高度或重量，實在難以界定蛋糕尺寸，加上她對烘焙不了解， 只好就此算了不再爭取。 店家解釋讓網友全看傻，「店家是對",
    "link": "https://udn.com/news/story/120912/9418939?from=udn-ch1_breaknews-1-0-news",
    "image": "https://pgw.udn.com.tw/gw/photo.php?u=https://uc.udn.com.tw/photo/t3/2026/04/02/34821933.jpg&M=1&s=Y&x=0&y=0&sw=1272&sh=848&exp=3600",
    "published_at": "2026-04-02 14:16"
  },
  {
    "title": "中職／台鋼集團不參與都更案投標 目標放在催生高雄巨蛋球場",
    "summary": "台鋼雄鷹隊自2022年創隊至今，持續深耕高雄在地，前年正式加入一軍行列，即以高雄澄清湖球場為主場，每年至少安排40場主場賽事；台鋼集團為了展現在地經營決心，更是斥資3億以上，歷時兩年在高雄路竹打造職業運動訓練基地「皇鷹學院」，自今年1月10日正式啟用，成為雄鷹訓練基地大本營。",
    "link": "https://udn.com/news/story/7001/9418995?from=udn-ch1_breaknews-1-0-news",
    "image": "https://pgw.udn.com.tw/gw/photo.php?u=https://uc.udn.com.tw/photo/t3/2026/04/02/34821971.jpg&M=1&s=Y&x=0&y=0&sw=1279&sh=853&exp=3600",
    "published_at": "2026-04-02 14:14"
  },
  {
    "title": "違法雇用少年還出言恐嚇 新北惡老闆起訴求重刑",
    "summary": "新北市一名黃姓人力業者去年6至8月間，竟涉嫌以每日1500元薪資，違法僱用一名年僅13歲的少年，從事爬高搬運物品及處理垃圾等工作。待少年欲離職，又揚言毆打予以恐嚇，遭新北地檢署依違反勞動基準法非法僱用未成年人工作、刑法恐嚇罪起訴，並依兒童及少年福利與權益保障法求處加重其刑2分之1。",
    "link": "https://udn.com/news/story/7321/9418993?from=udn-ch1_breaknews-1-0-news",
    "image": "https://pgw.udn.com.tw/gw/photo.php?u=https://uc.udn.com.tw/photo/t3/2026/04/02/34821970.jpg&M=1&s=Y&x=0&y=0&sw=1279&sh=853&exp=3600",
    "published_at": "2026-04-02 14:14"
  },
  {
    "title": "藍營小雞鄧凱勛拚板橋初選 找藍委洪孟楷助陣",
    "summary": "國民黨新北市議員初選即將登場，國民黨板橋區市議員參選人鄧凱勛今天邀請立委洪孟楷一同前往港德市場掃街。洪孟楷現場致贈鄧凱勛一份「人蔘」大禮，除為正在經歷初選高強度考驗的鄧凱勛養氣，期許他要「為藍營爭一口氣」，為藍營在板橋多爭取一席。",
    "link": "https://udn.com/news/story/124652/9418983?from=udn-ch1_breaknews-1-0-news",
    "image": "https://pgw.udn.com.tw/gw/photo.php?u=https://uc.udn.com.tw/photo/t3/2026/04/02/34821966.jpg&M=1&s=Y&x=0&y=0&sw=1279&sh=853&exp=3600",
    "published_at": "2026-04-02 14:13"
  },
  {
    "title": "總預算未審影響國防預算780億元 海馬士恐延遲交貨",
    "summary": "2026年度中央政府總預算案至今未審，國防部2日於例行記者會表示，估有21%國防預算無法按原訂期程執行，受影響預算為新台幣780億元；若未獲足額預算，如海馬士多管火箭系統、魚叉飛彈海岸防衛系統都可能發生廠商延遲交貨。",
    "link": "https://udn.com/news/story/10930/9418976?from=udn-ch1_breaknews-1-0-news",
    "image": "https://pgw.udn.com.tw/gw/photo.php?u=https://uc.udn.com.tw/photo/t3/2026/04/02/34821949.jpg&M=1&s=Y&x=0&y=0&sw=1280&sh=853&exp=3600",
    "published_at": "2026-04-02 14:13"
  },
  {
    "title": "強化居住安全 竹市擴大補助老舊大樓消防設備再增5項",
    "summary": "為提升老舊大樓火災防範能力，新竹市消防局持續推動「提升老舊大樓公共安全方案」，補助1995年6月27日前取得使照6樓以上大樓進行「3燈2器1門」（緊急照明燈、指示燈、滅火器、火警警報或廣播系統、防火門）維修更新，消防局說，115年度進一步擴大補助範圍，新增室內消防栓、自動灑水設備、泡沫滅火設備、消防專用蓄水池及緊急電源等5項。",
    "link": "https://udn.com/news/story/7324/9418978?from=udn-ch1_breaknews-1-0-news",
    "image": "https://pgw.udn.com.tw/gw/photo.php?u=https://uc.udn.com.tw/photo/t3/2026/04/02/34821958.jpg&M=1&s=Y&x=0&y=0&sw=1081&sh=720&exp=3600",
    "published_at": "2026-04-02 14:13"
  },
  {
    "title": "囂張竊賊狂偷17處魚塭電纜！被抓兩次「1萬就交保」高雄議員氣炸",
    "summary": "北高雄魚塭電纜遭竊案件頻傳引發眾怒，高市議員黃明太今日在議會質詢指出，多達17名養殖戶赴服務處集體陳情，自家魚塭電纜線同時間被偷，嫌犯不只偷剪電纜，還放火燒電纜以取得銅線銷售，警方好不容易抓到小偷之後，竟然接連兩次都獲得1萬元交保後返家，養殖戶終日惶惶不安。",
    "link": "https://udn.com/news/story/7327/9418971?from=udn-ch1_breaknews-1-0-news",
    "image": "https://pgw.udn.com.tw/gw/photo.php?u=https://uc.udn.com.tw/photo/t3/2026/04/02/34821935.jpg&M=1&s=Y&x=0&y=0&sw=1087&sh=725&exp=3600",
    "published_at": "2026-04-02 14:11"
  },
  {
    "title": "川普演說提油救火！股市總司令慘變反指標…股添樂：一路A下去股民哀嚎",
    "summary": "川普今早記者會中重申對伊朗的強硬立場，結果股市在他講話過程中卻逆勢下滑，成為提油救火的反指標，股民哀嚎四起。分析指出，市場情緒因川普的言論受到衝擊，反應激烈。",
    "link": "https://udn.com/news/story/12806/9418960?from=udn-ch1_breaknews-1-0-news",
    "image": "https://pgw.udn.com.tw/gw/photo.php?u=https://uc.udn.com.tw/photo/t3/2026/04/02/34821934.jpg&M=1&x=&y=&sw=&sh=&exp=3600",
    "published_at": "2026-04-02 14:07"
  },
  {
    "title": "祭祖也能添財旺運！命理師分享清明必做3事：不只是掃墓",
    "summary": "清明連假即將到來，許多人會提早回故鄉祭祖，祈求能獲得祖先庇護。命理專家周映君老師在節目《命運好好玩》中分享祭拜祖先時能獲得好運的3個方法，幫助你掃墓時能添德更添財。",
    "link": "https://udn.com/news/story/7268/9418742?from=udn-ch1_breaknews-1-0-news",
    "image": "https://pgw.udn.com.tw/gw/photo.php?u=https://uc.udn.com.tw/photo/t3/2026/04/02/34821637.jpg&M=1&s=Y&x=0&y=0&sw=1280&sh=853&exp=3600",
    "published_at": "2026-04-02 14:05"
  },
  {
    "title": "不是天災落石！大貨車惹禍…蘇花路廊驚現巨石",
    "summary": "台9丁線61.3公里處、花蓮秀林鄉和仁路段，今天中午出現一顆大石頭，公路局派員了解，發現是貨車載運時掉落的大石頭，已由業者處理完成，警方表示若違反道交條例將開單，道路受損部分公路局也要求償。",
    "link": "https://udn.com/news/story/7328/9418961?from=udn-ch1_breaknews-1-0-news",
    "image": "https://pgw.udn.com.tw/gw/photo.php?u=https://uc.udn.com.tw/photo/t3/2026/04/02/34821921.jpg&M=1&s=Y&x=0&y=0&sw=1280&sh=854&exp=3600",
    "published_at": "2026-04-02 14:03"
  },
  {
    "title": "立百病毒致死率最高75%！ 衛福部今公布列第五類法定傳染病",
    "summary": "印度先前爆發5例立百病毒感染個案，致死率達40至75%，衛福部今公告新增立百病毒感染症（Nipah Virus Infection）為第五類法定傳染病，疾管署依國際相關指引訂定病例定義，請醫師於臨床診治如發現符合通報定義病例，應於24小時內至傳染病通報系統NIDRS通報，並依感染管制措施指引進行疑似病例採檢送驗及隔離治療。",
    "link": "https://udn.com/news/story/7266/9418959?from=udn-ch1_breaknews-1-0-news",
    "image": "https://pgw.udn.com.tw/gw/photo.php?u=https://uc.udn.com.tw/photo/t3/2026/04/02/34821919.png&M=1&s=Y&x=0&y=0&sw=1264&sh=843&exp=3600",
    "published_at": "2026-04-02 14:02"
  },
  {
    "title": "議員指三芝福成活動中心老舊 另需地評估 新北市府：無急迫重建需求",
    "summary": "新北市三芝區多項公共設施老化問題浮上檯面。地方民代指出，三芝福成社區活動中心長期存在設施老舊與滲漏水等問題，要求市府加速規畫行政園區共構，新北市民政局則表示，福成活動中心耐震評估仍符合規定、使用年限未屆，暫無急迫重建需求；相關設施問題將配合工程改善，未來若推動行政園區再一併評估納入。",
    "link": "https://udn.com/news/story/7323/9418957?from=udn-ch1_breaknews-1-0-news",
    "image": "https://pgw.udn.com.tw/gw/photo.php?u=https://uc.udn.com.tw/photo/t3/2026/04/02/34821916.jpg&M=1&s=Y&x=0&y=0&sw=1279&sh=852&exp=3600",
    "published_at": "2026-04-02 14:01"
  },
  {
    "title": "網拍詐欺猖獗遊戲卡門票誘餌 新北警逮3嫌法辦",
    "summary": "新北警方今天表示，日前破獲漫畫「遊戲王」卡牌、販售熱門演唱會門票、三方詐欺等網拍詐欺案，警方分別逮捕3名犯嫌移送。詐團常...",
    "link": "https://udn.com/news/story/124490/9418855?from=udn-ch1_breaknews-1-0-news",
    "image": "https://pgw.udn.com.tw/gw/photo.php?u=https://p.udn.com.tw/upf/2017_news/noimg_cid6639_0.jpg",
    "published_at": "2026-04-02 13:59"
  },
  {
    "title": "不只要速審總預算 卓揆喊話立院：寬列才能因應國內外衝擊",
    "summary": "中央政府總預算僵局未解，國民黨立院黨團近日態度鬆動，最快將在10日黨團大會討論後，讓總預算付委審查。行政院長卓榮泰今（2）日再呼籲立法院速審總預算，才有助國家發展、中東情勢因應；他說，未來將秉持「當用則用，該省必省」原則，也提醒首長全力爭取，善加使用每項經費。",
    "link": "https://udn.com/news/story/6656/9418948?from=udn-ch1_breaknews-1-0-news",
    "image": "https://pgw.udn.com.tw/gw/photo.php?u=https://uc.udn.com.tw/photo/t3/2026/04/02/34821896.jpg&M=1&s=Y&x=0&y=0&sw=1280&sh=853&exp=3600",
    "published_at": "2026-04-02 13:57"
  },
  {
    "title": "不只要速審總預算 卓揆喊話立院：寬列才能因應國內外衝擊",
    "summary": "中央政府總預算僵局未解，國民黨立院黨團近日態度鬆動，最快將在10日黨團大會討論後，讓總預算付委審查。行政院長卓榮泰今（2）日再呼籲立法院速審總預算，才有助國家發展、中東情勢因應；他說，未來將秉持「當用則用，該省必省」原則，也提醒首長全力爭取，善加使用每項經費。",
    "link": "https://udn.com/news/story/6656/9418948?from=udn-ch1_breaknews-1-0-news",
    "image": "https://pgw.udn.com.tw/gw/photo.php?u=https://uc.udn.com.tw/photo/t3/2026/04/02/34821896.jpg&M=1&s=Y&x=0&y=0&sw=1280&sh=853&exp=3600",
    "published_at": "2026-04-02 13:57"
  },
  {
    "title": "MLB／道奇日本三本柱只有大谷奪勝 山本下一戰和岡本硬碰硬",
    "summary": "道奇隊日本投手山本由伸今天對守護者隊先發6局失兩分，優質先發吞下本季首敗，下次登板將於7日在多倫多對決藍鳥隊，首次和世界棒球經典賽隊友岡本和真交手，山本說：「岡本是非常優秀的打者，我會盡全力解決他。」",
    "link": "https://udn.com/news/story/6999/9418946?from=udn-ch1_breaknews-1-0-news",
    "image": "https://pgw.udn.com.tw/gw/photo.php?u=https://uc.udn.com.tw/photo/t3/2026/04/02/34821951.jpg&M=1&s=Y&x=0&y=0&sw=1279&sh=853&exp=3600",
    "published_at": "2026-04-02 13:56"
  },
  {
    "title": "「只是過去30天發文總結」專家狠酸川普伊朗演說 連「沒料」都算不上",
    "summary": "美國總統川普美東時間1日晚間就美伊戰爭向全美發表重大談話，但華府智庫昆西研究所（Quincy Institute）執行副總裁帕爾西（Trita Parsi）認為，演說未提出任何新內容，只是重申過去說法。",
    "link": "https://udn.com/news/story/124061/9418943?from=udn-ch1_breaknews-1-0-news",
    "image": "https://pgw.udn.com.tw/gw/photo.php?u=https://uc.udn.com.tw/photo/t3/2026/04/02/34821892.jpg&M=1&s=Y&x=0&y=0&sw=1280&sh=853&exp=3600",
    "published_at": "2026-04-02 13:55"
  },
  {
    "title": "產官學討論提升彰化花卉競爭力 結論：花卉與園藝生活化",
    "summary": "立法委員陳素月依據彰化縣花卉農業界反映，今在田尾鄉舉辦「「提升彰化花卉競爭力」產官學座談會，農政單位說明現階段研發及輔導的作為，農民陳述目前困境，除了越南花卉競爭力強，眾人都認為花卉與園藝都應生活化，增加國產花卉銷售量。",
    "link": "https://udn.com/news/story/7325/9418937?from=udn-ch1_breaknews-1-0-news",
    "image": "https://pgw.udn.com.tw/gw/photo.php?u=https://uc.udn.com.tw/photo/t3/2026/04/02/34821883.jpg&M=1&s=Y&x=0&y=0&sw=1080&sh=720&exp=3600",
    "published_at": "2026-04-02 13:54"
  },
  {
    "title": "富品建設成立都更整合服務中心 搶進自主都更商機",
    "summary": "房市轉型，都更升溫，看準政策趨勢與市場需求，富品建設日前於台北市信義區大道路成立「富品建設都更整合服務中心」，透過在地駐點服務平台，協助地主理解更新機制、保障權益，並縮短都更整合時程。",
    "link": "https://udn.com/news/story/7241/9418934?from=udn-ch1_breaknews-1-0-news",
    "image": "https://pgw.udn.com.tw/gw/photo.php?u=https://uc.udn.com.tw/photo/t3/2026/04/02/34821881.jpg&M=1&s=Y&x=0&y=0&sw=1279&sh=853&exp=3600",
    "published_at": "2026-04-02 13:54"
  },
  {
    "title": "春祭因公殉職病故警察典禮 警政署長張榮興感念伸張正義",
    "summary": "今年春祭歷年因公殉職暨病故警察人員典禮，今在台北市內湖區警察公墓舉行，由警政署長張榮興主祭，率警察代表祭悼追緬因公殉職、積勞病故的警察，感念盡忠職守伸張正義。",
    "link": "https://udn.com/news/story/7320/9418933?from=udn-ch1_breaknews-1-0-news",
    "image": "https://pgw.udn.com.tw/gw/photo.php?u=https://uc.udn.com.tw/photo/t3/2026/04/02/34821875.jpg&M=1&s=Y&x=0&y=0&sw=1280&sh=853&exp=3600",
    "published_at": "2026-04-02 13:53"
  },
  {
    "title": "台中豪宅市場韌性強 這案改寫社區新高紀錄",
    "summary": "在市場氛圍相對冷靜的當下，投資客全面退出，房市正式回歸居住本質的「自住客當家」時代。儘管整體環境趨於盤整，但台中各大熱門重劃區房價近年居高不墜，反而突顯七期重劃區的保值增值性。業界分析，七期房價表現長期被低估、顯得實在委屈，這股強勁的補漲動能支撐下，指標豪宅案在逆風中仍傳捷報，第1季寶輝、聯聚皆創下百萬成交單價，其中「寶輝101 Theater South」更改寫社區新高價，引發業界高度關注。",
    "link": "https://udn.com/news/story/7241/9418931?from=udn-ch1_breaknews-1-0-news",
    "image": "https://pgw.udn.com.tw/gw/photo.php?u=https://uc.udn.com.tw/photo/t3/2026/04/02/34821869.jpg&M=1&s=Y&x=0&y=0&sw=1280&sh=853&exp=3600",
    "published_at": "2026-04-02 13:52"
  },
  {
    "title": "躲陽台、浴室抽菸還是害到家人！ ADHD兒童高達88.6%曾暴露二手菸",
    "summary": "根據研究，家中有吸菸者，孩子即使未主動吸菸，仍會暴露在二手菸與三手菸中，導致多種呼吸道疾病與影響腦部發育。臨床研究更明確將二手菸暴露與兒童的心理健康問題，特別是注意力不足過動症（ADHD），有高達88.6%曾有明顯的二手菸暴露史，菸害不容小覷。",
    "link": "https://udn.com/news/story/7266/9418924?from=udn-ch1_breaknews-1-0-news",
    "image": "https://pgw.udn.com.tw/gw/photo.php?u=https://uc.udn.com.tw/photo/t3/2026/04/02/34821860.jpg&M=1&s=Y&x=0&y=0&sw=1280&sh=853&exp=3600",
    "published_at": "2026-04-02 13:51"
  },
  {
    "title": "強震重創將滿兩年 太魯閣辦淨灘宣告再出發",
    "summary": "0403地震將滿2周年，太魯閣國家公園管理處今天在崇德海灘舉辦淨灘活動，宣告震後再出發。太管處長劉守禮說，復建工程穩定進行，遊客也逐步回流，接下來將是重建的衝刺期，將以維護地景生態前提下持續修復，讓太魯閣更具安全與韌性。",
    "link": "https://udn.com/news/story/7328/9418921?from=udn-ch1_breaknews-1-0-news",
    "image": "https://pgw.udn.com.tw/gw/photo.php?u=https://uc.udn.com.tw/photo/t3/2026/04/02/34821857.jpg&M=1&s=Y&x=0&y=0&sw=1280&sh=853&exp=3600",
    "published_at": "2026-04-02 13:50"
  },
  {
    "title": "全台最大鎮之爭！草屯苦追2年多擠下竹東 終極目標也曝光",
    "summary": "南投草屯自2015年起躍升為「全台第一大鎮」，但在2024年2月被新竹竹東超車，歷經2年多時間追趕，上月底人口數9萬7972人，比竹東多了139人，重返「全台最大鎮」寶座。草屯鎮長簡賜勝再發豪語，希望能衝破十萬人升格為市。",
    "link": "https://udn.com/news/story/7325/9418919?from=udn-ch1_breaknews-1-0-news",
    "image": "https://pgw.udn.com.tw/gw/photo.php?u=https://uc.udn.com.tw/photo/t3/2026/04/02/34821854.jpg&M=1&s=Y&x=0&y=0&sw=1280&sh=853&exp=3600",
    "published_at": "2026-04-02 13:49"
  },
  {
    "title": "川普喊藥品課徵100%關稅 食藥署曝輸美藥品規模：輔導藥廠推國藥國造",
    "summary": "美國貿易代表署揭露，我國承諾接受美國食品藥物管理局（USFDA）對美生產藥物上市許可，不會再進入台灣時施以額外要求。對此，衛福部食藥署署長姜至剛指出，「魔鬼藏在細節裡」，僅美國製造藥品採簡化審查措施，雙方共通的審查項目不必重新審視，但人種差異仍是審查重點。另，因應美國藥品關稅喊漲，食藥署將輔導國內製藥界，推動「國藥國造」。",
    "link": "https://udn.com/news/story/6656/9418917?from=udn-ch1_breaknews-1-0-news",
    "image": "https://pgw.udn.com.tw/gw/photo.php?u=https://uc.udn.com.tw/photo/t3/2026/04/02/34821852.jpg&M=1&s=Y&x=0&y=0&sw=1279&sh=853&exp=3600",
    "published_at": "2026-04-02 13:48"
  },
  {
    "title": "物價波動公布「0800」檢舉專線 法務部：破壞市場秩序零容忍",
    "summary": "近日石油供應短缺，引發民生物資價格出現波動，法務部今天指出，為防堵不肖業者藉機囤貨、哄抬價格，本月3日起陸續召開跨部會「物價聯合稽查小組會議」深入盤點各類民生物資價量變化，研商啟動聯合稽查機制之時機。",
    "link": "https://udn.com/news/story/7266/9418915?from=udn-ch1_breaknews-1-0-news",
    "image": "https://pgw.udn.com.tw/gw/photo.php?u=https://uc.udn.com.tw/photo/t3/2026/04/02/34821845.jpg&M=1&s=Y&x=0&y=0&sw=1081&sh=721&exp=3600",
    "published_at": "2026-04-02 13:47"
  },
  {
    "title": "鄭麗君：美鋼鋁關稅無差別待遇 台灣藥品已爭取優惠",
    "summary": "美國總統川普最快周四宣布新版鋼鋁關稅制度，改採分級稅率以及以國家安全為由對進口藥品課徵高額關稅。對此，行政院副院長鄭麗君2日表示，我方在過去談判過程中即已了解，美方並未對任何國家提供鋼品相關優惠，至於藥品部分，在台美所簽署的投資MOU中，我方已成功爭取到相關優惠待遇。未來將持續密切關注美方關稅政策是否有進一步變動，並在既有談判成果基礎上，確保我國產業維持最佳優惠待遇。",
    "link": "https://udn.com/news/story/7238/9418913?from=udn-ch1_breaknews-1-0-news",
    "image": "https://pgw.udn.com.tw/gw/photo.php?u=https://uc.udn.com.tw/photo/t3/2026/04/02/34821879.jpg&M=1&s=Y&x=0&y=0&sw=1280&sh=853&exp=3600",
    "published_at": "2026-04-02 13:47"
  },
  {
    "title": "MLB／創126年唯二紀錄！洋基25歲強投：大家都討厭我們",
    "summary": "洋基隊25歲先發投手斯萊特勒（Cam Schlittler）今天再度繳出好投，主投6.1局只被敲2安，狂飆7次三振，無保送，無失分，幫助洋基以5：3力克水手隊。斯萊特勒賽後受訪時直言，「大家都討厭洋基」。 上周斯萊特勒對巨人隊，主投5.1局只被敲1安，狂飆8次三振沒失分。他賽後在社群平台X發文寫道「繼續討厭我們」，引發許多球迷批評。 今天斯萊特勒再度繳出好表現，本季2場登板，合計11.2局送出15次三振，沒保送，防禦率0.00，每局被上壘率0.26。數據專家夏普（Katie Sharp）統計，斯萊特勒成為1900年以來，第2位球季前2場累計15次以上三振、0失分、僅讓對手上壘3次以內的投手。上一位是2023年光芒隊投手拉斯穆森（Drew Rasmussen）。 斯萊特勒賽後受訪時解釋那則貼文，「我們是洋基隊，大家都討厭我們，我從中獲得樂趣。」 斯萊特勒還表示自己喜歡當Underdog（不被看好的一方），他說，「當然，我覺得洋基不是Underdog，但大家都在盯著我們，很多人不喜歡我們，也不喜歡我，這本來就是比賽",
    "link": "https://udn.com/news/story/6999/9418903?from=udn-ch1_breaknews-1-0-news",
    "image": "https://pgw.udn.com.tw/gw/photo.php?u=https://uc.udn.com.tw/photo/t3/2026/04/02/34821838.jpg&M=1&s=Y&x=0&y=0&sw=1280&sh=853&exp=3600",
    "published_at": "2026-04-02 13:46"
  },
  {
    "title": "川普一席話難擋節前賣壓 台股收跌602點高低震盪近千點",
    "summary": "台股2日收盤下跌602.39點，終場以32,572.43點作收，成交量6,729.07億元；台積電（2330）收盤價1,810元，下跌45元，跌幅2.43%。台股指數今從開高走高到33,497點一路下滑至32,516點，高低差距981點，跌破5日均線；市場情緒變化之大除連續假期到來，投資人不願追價，甚至降低持股部位；美國總統川普最新演講內容出來後，亞洲主要股市一路走跌，台股賣壓也隨之出籠。",
    "link": "https://udn.com/news/story/7251/9418908?from=udn-ch1_breaknews-1-0-news",
    "image": "https://pgw.udn.com.tw/gw/photo.php?u=https://uc.udn.com.tw/photo/t3/2026/04/02/34821871.jpg&M=1&s=Y&x=0&y=0&sw=1266&sh=844&exp=3600",
    "published_at": "2026-04-02 13:46"
  },
  {
    "title": "朱政騏涉共諜火速切割 民進黨北市黨部：除名、開除黨籍",
    "summary": "檢調再查獲綠營涉共諜案，被捲入的是通過初選的民進黨台北市中山大同議員參選人朱政騏，民進黨台北市黨部火速處理，中午臨時評委會做出決定，取消朱政騏參選資格，開除黨籍，不能代表民進黨參選。",
    "link": "https://udn.com/news/story/120838/9418905?from=udn-ch1_breaknews-1-0-news",
    "image": "https://pgw.udn.com.tw/gw/photo.php?u=https://uc.udn.com.tw/photo/t3/2026/04/02/34821837.jpg&M=1&s=Y&x=0&y=0&sw=852&sh=568&exp=3600",
    "published_at": "2026-04-02 13:44"
  },
  {
    "title": "朱政騏涉共諜火速切割 民進黨北市黨部嚴厲處分：除名、開除黨籍",
    "summary": "檢調再查獲綠營涉共諜案，被捲入的是通過初選的民進黨台北市中山大同議員參選人朱政騏，民進黨台北市黨部火速處理，中午臨時評委會做出決定，取消朱政騏參選資格，開除黨籍，不能代表民進黨參選。",
    "link": "https://udn.com/news/story/6656/9418905?from=udn-ch1_breaknews-1-0-news",
    "image": "https://pgw.udn.com.tw/gw/photo.php?u=https://uc.udn.com.tw/photo/t3/2026/04/02/34821837.jpg&M=1&s=Y&x=0&y=0&sw=852&sh=568&exp=3600",
    "published_at": "2026-04-02 13:44"
  },
  {
    "title": "紓解水庫壓力！桃園北區再生水中心首期啟用 日供4萬噸",
    "summary": "桃園北區再生水中心第一期工程今正式啟用，預計每日可供應4萬噸再生水，供亞東石化、南亞塑膠錦興廠及中油桃園煉油廠等企業使用，有效紓解石門水庫供水壓力。市府表示，待第二期、第三期工程陸續完工，整體供水量將提升至每日11萬噸，成為北台灣規模最大的再生水系統，為桃園產業打造穩定的「第二水龍頭」。",
    "link": "https://udn.com/news/story/7324/9418901?from=udn-ch1_breaknews-1-0-news",
    "image": "https://pgw.udn.com.tw/gw/photo.php?u=https://uc.udn.com.tw/photo/t3/2026/04/02/34821832.jpg&M=1&s=Y&x=0&y=0&sw=1280&sh=853&exp=3600",
    "published_at": "2026-04-02 13:43"
  },
  {
    "title": "1拆7後飆漲逾2倍！00663L股價衝60.15元…小資族瘋搶正2ETF",
    "summary": "台股因地緣政治影響出現劇烈波動，槓桿型ETF成為投資焦點。00663L分割後股價飆漲逾2倍，成功吸引小資族進場。專家指出，短期內市場或受壓雖然長期仍看好AI應用帶來的支持。",
    "link": "https://udn.com/news/story/123006/9418854?from=udn-ch1_breaknews-1-0-news",
    "image": "https://pgw.udn.com.tw/gw/photo.php?u=https://uc.udn.com.tw/photo/t3/2026/04/02/34821818.jpg&M=1&x=&y=&sw=&sh=&exp=3600",
    "published_at": "2026-04-02 13:40"
  },
  {
    "title": "防中東戰事衝擊 農業部：肥料供到年底無虞 農機用油將祭補貼",
    "summary": "因應中東戰事爆發，造成能源價格提高，進而推升油、電及肥料等農業生產資材成本上漲壓力。農業部今於行政院報告「中東情勢因應—我國農業生產資材穩定措施」。農業部表示，目前肥料庫存原料足供至本年8到12月需求。農漁業用油補貼部分，目前農機用油已免徵5%營業稅，後續若油價超過中油公司公告牌價基準價格，即補貼漲幅的50%。",
    "link": "https://udn.com/news/story/7266/9418892?from=udn-ch1_breaknews-1-0-news",
    "image": "https://pgw.udn.com.tw/gw/photo.php?u=https://uc.udn.com.tw/photo/t3/2026/04/02/34821823.jpg&M=1&s=Y&x=0&y=0&sw=1280&sh=853&exp=3600",
    "published_at": "2026-04-02 13:39"
  },
  {
    "title": "被爆共諜案遭「刻意阻擋」提名參選北市議員？朱政騏：不能說沒有",
    "summary": "檢調再查獲綠營涉共諜案，這次被捲入的是通過初選的民進黨台北市中山大同議員擬參選人朱政騏。因民進黨下周三將正式提名北市議員參選人，此時被爆共諜案，朱政騏說，刻意阻擋提名的動作，不能說沒有。",
    "link": "https://udn.com/news/story/120838/9418890?from=udn-ch1_breaknews-1-0-news",
    "image": "https://pgw.udn.com.tw/gw/photo.php?u=https://uc.udn.com.tw/photo/t3/2026/04/02/34821820.jpg&M=1&s=Y&x=0&y=0&sw=1279&sh=853&exp=3600",
    "published_at": "2026-04-02 13:39"
  },
  {
    "title": "房仲亞太球場掌摑工讀生！神隱迄今吐心聲：一時失控感到懊悔想道歉",
    "summary": "49歲蔣姓男子上月29日在亞太國際棒球訓練中心成棒主球場啟用、賴清德總統親臨觀賽的首場中華職棒例行賽場邊，掌摑20歲蔡姓工讀生，引爆網友公憤，幸福家不動產隔天立即將蔣開除，蔣事發後神隱迄今；據了解，昨天蔣向前雇主表達想要向工讀生道歉，卻聯繫不上。",
    "link": "https://udn.com/news/story/7320/9418883?from=udn-ch1_breaknews-1-0-news",
    "image": "https://pgw.udn.com.tw/gw/photo.php?u=https://uc.udn.com.tw/photo/t3/2026/04/02/34821811.jpg&M=1&s=Y&x=1&y=59&sw=747&sh=498&exp=3600",
    "published_at": "2026-04-02 13:37"
  },
  {
    "title": "綠涉共諜再+1 馬文君：坐等賴總統、王定宇講出什麼幹話？",
    "summary": "民進黨總統府副秘書長何志偉立委時期的特助朱政騏，涉嫌利用職權偷拍機密文件再傳給大陸人士，遭北檢依國安法起訴。國民黨立委馬文君在臉書上質疑，民進黨根本不在乎自己黨員是共諜，即便已經被偵辦，還能參加初選，她這次坐等這回賴清德總統、民進黨立委王定宇又會講出什麼幹話。",
    "link": "https://udn.com/news/story/120838/9418871?from=udn-ch1_breaknews-1-0-news",
    "image": "https://pgw.udn.com.tw/gw/photo.php?u=https://uc.udn.com.tw/photo/t3/2026/04/02/34821798.jpg&M=1&s=Y&x=0&y=0&sw=1280&sh=853&exp=3600",
    "published_at": "2026-04-02 13:34"
  },
  {
    "title": "全本芭蕾舞劇《唐吉訶德》今夏登國家戲劇院 雙人套票95折現正熱賣中",
    "summary": "被譽為「西班牙文化大使」的西班牙國家舞團，將由遠百獨家呈獻，於今年7月23日至7月25日重磅登上國家戲劇院舞台，隆重呈獻古典芭蕾經典鉅作《唐吉訶德》舞劇。該劇不僅是舞團最具代表性的劇目，也象徵舞團藝術發展的成熟與深化，展現其作為西班牙當代舞壇旗艦團隊的國際影響力。全本芭蕾舞劇《唐吉訶德》雙人套票95折目前於udn售票網熱賣中，把握機會一睹國家級舞團帶來的舞蹈盛宴！",
    "link": "https://udn.com/news/story/7270/9418080?from=udn-ch1_breaknews-1-0-news",
    "image": "https://pgw.udn.com.tw/gw/photo.php?u=https://uc.udn.com.tw/photo/t3/2026/04/02/34820388.jpg&M=1&s=Y&x=0&y=389&sw=909&sh=606&exp=3600",
    "published_at": "2026-04-02 13:34"
  },
  {
    "title": "漲價仍不敷成本 日航與全日空考慮修改制度",
    "summary": "美國與以色列攻擊伊朗之後原油價格大漲，日本航空與全日空預計從6月起，調漲從日本出發、國際線所收取的燃油附加費，同時將評估...",
    "link": "https://udn.com/news/story/6811/9418723?from=udn-ch1_breaknews-1-0-news",
    "image": "https://pgw.udn.com.tw/gw/photo.php?u=https://uc.udn.com.tw/photo/t3/2026/04/02/34821788.jpg&M=1&s=Y&x=0&y=0&sw=1280&sh=853&exp=3600",
    "published_at": "2026-04-02 13:33"
  },
  {
    "title": "陸網友買「速效救心丸」後竟被註銷駕照？大數據篩檢引發隱私爭議",
    "summary": "陸媒報導，大陸廈門市民陳先生收到手機簡訊，被告知因有精神類藥品購買紀錄，涉嫌患有「妨礙安全駕駛疾病」，須30日內到交警支隊註銷駕駛證，逾期將公告作廢。此事迅速在大陸網上引發熱議。結果不少地方都有網民曾表示有類似經歷，因為購買鎮靜類、治療心血管疾病的藥物，而收到可能被註銷駕駛證的通知。",
    "link": "https://udn.com/news/story/7332/9418852?from=udn-ch1_breaknews-1-0-news",
    "image": "https://pgw.udn.com.tw/gw/photo.php?u=https://uc.udn.com.tw/photo/t3/2026/04/02/34821772.png&M=1&s=Y&x=0&y=0&sw=1279&sh=853&exp=3600",
    "published_at": "2026-04-02 13:29"
  },
  {
    "title": "台南螢光花泉季全攻略 梅嶺賞螢7日開搶 賞花泡湯一次玩",
    "summary": "2026台南螢光花泉季將於4月11日至5月3日在楠西區登場，台南市政府觀光旅遊局今天舉辦宣傳記者會，宣布以「花泉共舞」、「螢向幸福」、「解鎖計畫」及「漫遊之旅」四大主題，串聯龜丹溫泉、梅嶺賞螢、桐花季與地方產業，打造為期近1個月的春季觀光活動。",
    "link": "https://udn.com/news/story/7326/9418847?from=udn-ch1_breaknews-1-0-news",
    "image": "https://pgw.udn.com.tw/gw/photo.php?u=https://uc.udn.com.tw/photo/t3/2026/04/02/34821766.jpg&M=1&s=Y&x=0&y=0&sw=1279&sh=853&exp=3600",
    "published_at": "2026-04-02 13:27"
  },
  {
    "title": "國票金股東會紀念品出爐 「高級法蘭絨毯」零股領取2大條件曝光",
    "summary": "國票金（2889）將於5月29日舉行股東常會，並進行董事改選。日前董事會通過採購115年度股東會紀念品預算案，將原先的50元提高到300元，國票金2日也公告，今年將送出「高級法蘭絨毯」。根據集保中心統計，國票金股東目前大約21.9萬人。",
    "link": "https://udn.com/news/story/7252/9418845?from=udn-ch1_breaknews-1-0-news",
    "image": "https://pgw.udn.com.tw/gw/photo.php?u=https://uc.udn.com.tw/photo/t3/2026/04/02/34821796.jpg&M=1&s=Y&x=0&y=85&sw=1280&sh=853&exp=3600",
    "published_at": "2026-04-02 13:27"
  },
  {
    "title": "國內檢出首例人類H7流感個案 疾管署：下午4點說明",
    "summary": "國內檢出首例人類感染H7流感個案，疾管署今下午四點將舉行臨時記者會，由疾管署長羅一鈞親上火線說明說明檢出國內首例人類感染H7流感個案情形。同步出席記者還有副署長曾淑慧長、防疫醫師及防檢署副署長傅學理。",
    "link": "https://udn.com/news/story/7266/9418844?from=udn-ch1_breaknews-1-0-news",
    "image": "https://pgw.udn.com.tw/gw/photo.php?u=https://uc.udn.com.tw/photo/t3/2026/04/02/34821765.jpg&M=1&s=Y&x=0&y=0&sw=1280&sh=853&exp=3600",
    "published_at": "2026-04-02 13:26"
  },
  {
    "title": "距登機不到2小時！加籍女遊客遺失護照 海山警30分鐘神救援",
    "summary": "加拿大籍女子Karen與友人Jean日前來台觀光，不料上周六（28日）準備至桃機搭機返國途中，遺失裝有護照、現金以及筆電的背包，但距搭機時間僅剩不到2個小時。海山警獲報調閱監視器，短短30分鐘內協助尋回失物，讓2人順利趕上返國班機。",
    "link": "https://udn.com/news/story/7320/9418842?from=udn-ch1_breaknews-1-0-news",
    "image": "https://pgw.udn.com.tw/gw/photo.php?u=https://uc.udn.com.tw/photo/t3/2026/04/02/34821763.jpg&M=1&s=Y&x=0&y=0&sw=1279&sh=853&exp=3600",
    "published_at": "2026-04-02 13:26"
  },
  {
    "title": "涉共諜案恐丟議員參選人資格 朱政騏：不會脫黨參選",
    "summary": "檢調再查獲綠營涉共諜案，被捲入的是通過初選的民進黨台北市中山大同議員參選人朱政騏，民進黨台北市黨部火速處理，中午臨評委會，並請朱政騏到場說明。對於恐影響參選資格，朱政騏說，他絕對不會脫黨參選，他絕對支持民進黨要團結。",
    "link": "https://udn.com/news/story/120838/9418841?from=udn-ch1_breaknews-1-0-news",
    "image": "https://pgw.udn.com.tw/gw/photo.php?u=https://uc.udn.com.tw/photo/t3/2026/04/02/34821762.jpg&M=1&s=Y&x=0&y=0&sw=1279&sh=853&exp=3600",
    "published_at": "2026-04-02 13:25"
  },
  {
    "title": "涉共諜案恐丟議員參選人資格 朱政騏：不會脫黨參選",
    "summary": "檢調再查獲綠營涉共諜案，被捲入的是通過初選的民進黨台北市中山大同議員參選人朱政騏，民進黨台北市黨部火速處理，中午臨評委會，並請朱政騏到場說明。對於恐影響參選資格，朱政騏說，他絕對不會脫黨參選，他絕對支持民進黨要團結。",
    "link": "https://udn.com/news/story/6656/9418841?from=udn-ch1_breaknews-1-0-news",
    "image": "https://pgw.udn.com.tw/gw/photo.php?u=https://uc.udn.com.tw/photo/t3/2026/04/02/34821762.jpg&M=1&s=Y&x=0&y=0&sw=1279&sh=853&exp=3600",
    "published_at": "2026-04-02 13:25"
  },
  {
    "title": "台灣開放美國柿子零關稅進口 農會承諾保價收購顧農民",
    "summary": "台灣擬鬆綁農產品特別防衛措施SSG，不再對美國的柿子、檳榔等農產品課徵關稅，可能對嘉義農業產生衝擊，引發農民關注。番路鄉農會今天表示，美國進口品種為甜柿，不利於加工，將持續保價收購台灣牛心柿；檳榔目前則以東南亞進口大宗，農業處評估對農民影響不大。",
    "link": "https://udn.com/news/story/7314/9418840?from=udn-ch1_breaknews-1-0-news",
    "image": "https://pgw.udn.com.tw/gw/photo.php?u=https://uc.udn.com.tw/photo/t3/2026/04/02/34821758.jpg&M=1&s=Y&x=0&y=0&sw=1280&sh=854&exp=3600",
    "published_at": "2026-04-02 13:24"
  },
  {
    "title": "總預算卡關 國防部：除海馬士等裝備 6億外部清潔人力也沒著落",
    "summary": "115年度中央政府總預算案持續卡關，雖然國民黨立院黨團釋出願意付委排審的主張，國防部今天指出，今年度國防部歲出預算除了正在交運中的第一批海馬士多管火箭、無人機產業園區等案件外，包括第一預備金及外部清潔人員費用等，合計約有780億元受到影響無法按原訂期程執行。",
    "link": "https://udn.com/news/story/10930/9418839?from=udn-ch1_breaknews-1-0-news",
    "image": "https://pgw.udn.com.tw/gw/photo.php?u=https://uc.udn.com.tw/photo/t3/2026/04/02/34821757.jpg&M=1&s=Y&x=0&y=0&sw=1279&sh=853&exp=3600",
    "published_at": "2026-04-02 13:23"
  },
  {
    "title": "避開熱量陷阱！營養師曝手搖飲「加料」綠燈區",
    "summary": "手搖飲被喻為精神支柱，尤其是珍珠、粉粿、茶凍等「加料」的咀嚼感，帶來療癒滿足。營養師張宜婷表示，高熱量配料直逼200大卡，等同1碗白飯，長期喝恐導致肥胖與血糖波動。想喝加料手搖飲並非不行，而是要遵循減糖原則，例如仙草、愛玉、蘆薈等熱量較低的「綠燈配料」，減少身體負擔。",
    "link": "https://udn.com/news/story/7266/9418838?from=udn-ch1_breaknews-1-0-news",
    "image": "https://pgw.udn.com.tw/gw/photo.php?u=https://uc.udn.com.tw/photo/t3/2026/04/02/34821756.jpg&M=1&s=Y&x=0&y=0&sw=1278&sh=851&exp=3600",
    "published_at": "2026-04-02 13:22"
  },
  {
    "title": "SSG防線鬆動 養豬產業憂大量進口豬衝擊本土市場",
    "summary": "根據台美隊等貿易協議(ART)，台灣已承諾對99%原須課徵關稅的稅目，取消或調降關稅，來自美國的農產品也將不再被台灣根據WTO「農業協定」所實施的SSG，課徵任何關稅。過去包括畜牧下腳料等項目曾適用SSG機制，如今保護機制鬆動，養豬產業憂心，國外豬肉產品恐大量湧入，衝擊本土市場。",
    "link": "https://udn.com/news/story/7314/9418834?from=udn-ch1_breaknews-1-0-news",
    "image": "https://pgw.udn.com.tw/gw/photo.php?u=https://uc.udn.com.tw/photo/t3/2026/04/02/34821753.jpg&M=1&s=Y&x=0&y=0&sw=1280&sh=853&exp=3600",
    "published_at": "2026-04-02 13:19"
  },
  {
    "title": "龜山失聯移工跳車狂奔 桃園軍警包抄成功制伏",
    "summary": "桃園市龜山警分局員警昨(1)日晚間21時20分許於復興街巡邏時，發現一台可疑車輛，上前盤查，車上3人神情緊張，隨後跳車逃逸，警方立即展開追緝，附近陸軍269旅官兵們見狀，亦加入圍捕行列，在軍警合作之下，成功制伏3人。經查3人均為印尼籍失聯移工，全案移請移民署桃園專勤隊收容靜候遣返。",
    "link": "https://udn.com/news/story/7320/9418759?from=udn-ch1_breaknews-1-0-news",
    "image": "https://pgw.udn.com.tw/gw/photo.php?u=https://p.udn.com.tw/upf/2017_news/noimg_cid6639_3.jpg",
    "published_at": "2026-04-02 13:18"
  },
  {
    "title": "涉當共諜被起訴 朱政騏：完全不是「共諜案」是家事糾紛",
    "summary": "民進黨北市議員擬參選人朱政騏涉當共諜被起訴，朱政騏下午受訪指出，其實這完全不是一個「共諜案」這跟之前大家看到的共諜案，其實是完全是兩回事，這就是「家事」糾紛。",
    "link": "https://udn.com/news/story/120838/9418822?from=udn-ch1_breaknews-1-0-news",
    "image": "https://pgw.udn.com.tw/gw/photo.php?u=https://uc.udn.com.tw/photo/t3/2026/04/02/34821733.jpg&M=1&s=Y&x=0&y=0&sw=1279&sh=853&exp=3600",
    "published_at": "2026-04-02 13:16"
  },
  {
    "title": "涉當共諜被起訴 朱政騏：完全不是「共諜案」是家事糾紛",
    "summary": "民進黨北市議員擬參選人朱政騏涉當共諜被起訴，朱政騏下午受訪指出，其實這完全不是一個「共諜案」這跟之前大家看到的共諜案，其實是完全是兩回事，這就是「家事」糾紛。",
    "link": "https://udn.com/news/story/6656/9418822?from=udn-ch1_breaknews-1-0-news",
    "image": "https://pgw.udn.com.tw/gw/photo.php?u=https://uc.udn.com.tw/photo/t3/2026/04/02/34821733.jpg&M=1&s=Y&x=0&y=0&sw=1279&sh=853&exp=3600",
    "published_at": "2026-04-02 13:16"
  },
  {
    "title": "因應中東局勢 政院：三鐵、客運、國內航線票價凍漲",
    "summary": "中東戰事未歇，行政院副院長鄭麗君今（2）日指出，已要求高鐵、台鐵、捷運、公車、客運票價不調漲，另基於公平原則，國內航線票價亦協調暫緩調整，確保花東、離島民眾權益。",
    "link": "https://udn.com/news/story/7314/9418818?from=udn-ch1_breaknews-1-0-news",
    "image": "https://pgw.udn.com.tw/gw/photo.php?u=https://uc.udn.com.tw/photo/t3/2026/04/02/34821728.jpg&M=1&s=Y&x=0&y=0&sw=1279&sh=853&exp=3600",
    "published_at": "2026-04-02 13:15"
  }
]